{
	"pageNo": 1,
	"pageSize": 30,
	"orderBy": "zllrsj",
	"orderDir": "desc",
	"countTotal": true,
	"result": [{
		"zlcode": "0000000002016042200001",
		"zlwfid": null,
		"activityid": null,
		"zljm": "41631",
		"zltitle": "财政部 国家税务总局关于营业税改征增值税试点有关文化事业建设费政策及征收管理问题的通知",
		"zlgjz": "文化事业建设费 营改增 广告服务",
		"zlflag": "1",
		"zltype": "“1“000000000122“00000000012203“",
		"zlhytype": "00000000000000000000040",
		"zllywj": "0000000002016042200001.voc",
		"zlczwj": null,
		"zllrr": "zscj005",
		"zllrsj": "2016-04-22",
		"zllrdw": "知识库运维组",
		"zlzt": "60",
		"zlsfyx": "0",
		"zlsffb": "1",
		"zlfbr": "system",
		"zlly": null,
		"zlsz": "0",
		"zlwh": "财税〔2016〕25号",
		"zlfwdw": "财政部 国家税务总局",
		"zlbfrq": 1459148005000,
		"zlsxrq": null,
		"zlssrq": 1462085605000,
		"zlwjdj": "3",
		"zlsydj": "0",
		"zlnowshr": null,
		"zlnowshjs": null,
		"zlnowjg": null,
		"zlnowbm": null,
		"zlzhczr": "zssh001",
		"zlzhczsj": 1461308336000,
		"lastczr": null,
		"zlqzz": null,
		"zlwxyy": null,
		"zlzy": null,
		"zlpz": null,
		"zlsfgk": "0",
		"zlfbrq": 1461308336000,
		"zlcxyy": null,
		"zlnzoa": null,
		"zloaid": null,
		"zldq": "00000000",
		"zldqmc": "中华人民共和国",
		"zlfwzg": null,
		"zlsfdl": "0",
		"zlsfzcyh": "1",
		"zldxlx": "00000000000000000000003",
		"zldqbbh": "0000000002016042200001002",
		"zldffg": null,
		"zlxf": null,
		"zlywczr": null,
		"zltypemc": "税收法规->其他地方规费->文化事业建设费",
		"zlhytypemc": "通用政策",
		"zlfz": 31,
		"zlisdel": "0",
		"zlwzfgbh": null,
		"zldxlxmc": "全部",
		"zlcxlcid": null,
		"gxsj": "2016-04-22 14:58:56",
		"bbh": null,
		"jhzt": "1",
		"xzqh": "000000000",
		"zlcxsqr": null,
		"zldlssid": "0",
		"zldlxh": null,
		"zlsxczbs": "0",
		"zlsfjs": "0",
		"zlsfzjsh": "0",
		"zlzgdw": null,
		"zlzgdwmc": null
	}, {
		"zlcode": "0000000002010102724390",
		"zlwfid": null,
		"activityid": null,
		"zljm": "26634",
		"zltitle": "财政部 国家税务总局关于国家石油储备基地建设有关税收政策的通知",
		"zlgjz": "石油 储备 基地 建设",
		"zlflag": "1",
		"zltype": "“1“000000000118“,“1“000000000117“,“1“000000000111“,“1“000000000112“,“1“000000000122“00000000012201“,“1“000000000109“,“1“000000000105“",
		"zlhytype": "00000000000000000000040",
		"zllywj": "0000000002010102724390.voc",
		"zlczwj": null,
		"zllrr": "总局超管",
		"zllrsj": "2016-02-23",
		"zllrdw": null,
		"zlzt": "60",
		"zlsfyx": "0",
		"zlsffb": "1",
		"zlfbr": "system",
		"zlly": null,
		"zlsz": "0",
		"zlwh": "财税〔2005〕23号",
		"zlfwdw": "财政部 国家税务总局",
		"zlbfrq": 1110875220000,
		"zlsxrq": null,
		"zlssrq": null,
		"zlwjdj": "3",
		"zlsydj": "0",
		"zlnowshr": null,
		"zlnowshjs": null,
		"zlnowjg": null,
		"zlnowbm": null,
		"zlzhczr": "zssh001",
		"zlzhczsj": 1456216947000,
		"lastczr": null,
		"zlqzz": null,
		"zlwxyy": null,
		"zlzy": null,
		"zlpz": "Z-1-118",
		"zlsfgk": "0",
		"zlfbrq": 1456216947000,
		"zlcxyy": null,
		"zlnzoa": null,
		"zloaid": null,
		"zldq": "00000000",
		"zldqmc": "中华人民共和国",
		"zlfwzg": null,
		"zlsfdl": "0",
		"zlsfzcyh": "1",
		"zldxlx": "00000000000000000000003",
		"zldqbbh": "00000000000000000143585002",
		"zldffg": null,
		"zlxf": null,
		"zlywczr": null,
		"zltypemc": "税收法规->营业税；税收法规->城市维护建设税；税收法规->其他地方规费->教育费附加；税收法规->城镇土地使用税；税收法规->印花税；税收法规->耕地占用税；税收法规->契税",
		"zlhytypemc": "通用政策",
		"zlfz": 13,
		"zlisdel": "0",
		"zlwzfgbh": null,
		"zldxlxmc": "全部",
		"zlcxlcid": null,
		"gxsj": "2016-02-23 16:42:27",
		"bbh": null,
		"jhzt": "1",
		"xzqh": "000000000",
		"zlcxsqr": null,
		"zldlssid": "0",
		"zldlxh": null,
		"zlsxczbs": null,
		"zlsfjs": "0",
		"zlsfzjsh": "0",
		"zlzgdw": null,
		"zlzgdwmc": null
	}, {
		"zlcode": "0000000002016020500003",
		"zlwfid": null,
		"activityid": null,
		"zljm": "41044",
		"zltitle": "国家税务总局关于合理简并纳税人申报缴税次数的公告",
		"zlgjz": "小规模纳税人 申报 应纳税额 季度 零申报 定期定额",
		"zlflag": "1",
		"zltype": "“1“000000000122“00000000012201“,“1“000000000122“00000000012203“,“1“000000000106“,“1“000000000104“,“1“000000000103“,“1“000000000102“,“1“000000000122“00000000012206“",
		"zlhytype": "00000000000000000000040",
		"zllywj": "0000000002016020500003.voc",
		"zlczwj": null,
		"zllrr": "zscj005",
		"zllrsj": "2016-02-22",
		"zllrdw": "知识库运维组",
		"zlzt": "60",
		"zlsfyx": "0",
		"zlsffb": "1",
		"zlfbr": "system",
		"zlly": null,
		"zlsz": "0",
		"zlwh": "国家税务总局公告2016年第6号",
		"zlfwdw": "国家税务总局",
		"zlbfrq": 1454298346000,
		"zlsxrq": null,
		"zlssrq": 1459482346000,
		"zlwjdj": "3",
		"zlsydj": "0",
		"zlnowshr": null,
		"zlnowshjs": null,
		"zlnowjg": null,
		"zlnowbm": null,
		"zlzhczr": "zssh001",
		"zlzhczsj": 1456112935000,
		"lastczr": null,
		"zlqzz": null,
		"zlwxyy": null,
		"zlzy": null,
		"zlpz": null,
		"zlsfgk": "0",
		"zlfbrq": 1456112935000,
		"zlcxyy": null,
		"zlnzoa": null,
		"zloaid": null,
		"zldq": "00000000",
		"zldqmc": "中华人民共和国",
		"zlfwzg": null,
		"zlsfdl": "0",
		"zlsfzcyh": "0",
		"zldxlx": "00000000000000000000003",
		"zldqbbh": "0000000002016020500003005",
		"zldffg": null,
		"zlxf": null,
		"zlywczr": null,
		"zltypemc": "税收法规->其他地方规费->教育费附加；税收法规->其他地方规费->文化事业建设费；税收法规->企业所得税；税收法规->消费税；税收法规->增值税；税收法规->征收管理；税收法规->其他地方规费->城市维护建设税",
		"zlhytypemc": "通用政策",
		"zlfz": 55,
		"zlisdel": "0",
		"zlwzfgbh": null,
		"zldxlxmc": "全部",
		"zlcxlcid": null,
		"gxsj": "2016-02-22 11:48:55",
		"bbh": null,
		"jhzt": "1",
		"xzqh": "000000000",
		"zlcxsqr": null,
		"zldlssid": "0",
		"zldlxh": null,
		"zlsxczbs": "0",
		"zlsfjs": "0",
		"zlsfzjsh": "0",
		"zlzgdw": null,
		"zlzgdwmc": null
	}, {
		"zlcode": "1450000002016020100004",
		"zlwfid": null,
		"activityid": null,
		"zljm": "21032",
		"zltitle": "财政部 国家税务总局关于取消、停征和整合部分政府性基金项目等有关问题的通知",
		"zlgjz": "价格调节 基金 停征",
		"zlflag": "1",
		"zltype": "“1“000000000122“",
		"zlhytype": "00000000000000000000040",
		"zllywj": "1450000002016020100004.voc",
		"zlczwj": null,
		"zllrr": "杨玲",
		"zllrsj": "2016-02-19",
		"zllrdw": "12366纳税服务热线",
		"zlzt": "60",
		"zlsfyx": "0",
		"zlsffb": "1",
		"zlfbr": "杨玲",
		"zlly": null,
		"zlsz": "1",
		"zlwh": "财税（2016）11号",
		"zlfwdw": "财政部 国家税务总局",
		"zlbfrq": 1454029647000,
		"zlsxrq": null,
		"zlssrq": null,
		"zlwjdj": "3",
		"zlsydj": "1",
		"zlnowshr": null,
		"zlnowshjs": null,
		"zlnowjg": null,
		"zlnowbm": null,
		"zlzhczr": "杨玲",
		"zlzhczsj": 1455843965000,
		"lastczr": null,
		"zlqzz": null,
		"zlwxyy": null,
		"zlzy": null,
		"zlpz": null,
		"zlsfgk": "0",
		"zlfbrq": 1455843965000,
		"zlcxyy": null,
		"zlnzoa": null,
		"zloaid": null,
		"zldq": "45000000",
		"zldqmc": "广西壮族自治区",
		"zlfwzg": null,
		"zlsfdl": "0",
		"zlsfzcyh": "0",
		"zldxlx": "00000000000000000000003",
		"zldqbbh": "1450000002016020100004004",
		"zldffg": null,
		"zlxf": null,
		"zlywczr": null,
		"zltypemc": "税收法规->其他地方规费",
		"zlhytypemc": "通用政策",
		"zlfz": 175,
		"zlisdel": "0",
		"zlwzfgbh": null,
		"zldxlxmc": "全部",
		"zlcxlcid": null,
		"gxsj": null,
		"bbh": null,
		"jhzt": "1",
		"xzqh": "145000000",
		"zlcxsqr": null,
		"zldlssid": "0",
		"zldlxh": null,
		"zlsxczbs": "0",
		"zlsfjs": "0",
		"zlsfzjsh": "0",
		"zlzgdw": null,
		"zlzgdwmc": null
	}, {
		"zlcode": "0000000002016020100005",
		"zlwfid": null,
		"activityid": null,
		"zljm": "41009",
		"zltitle": "财政部关于取消 停征和整合部分政府性基金项目等有关问题的通知",
		"zlgjz": "基金 水泥 水库 ",
		"zlflag": "1",
		"zltype": "“1“000000000122“",
		"zlhytype": "00000000000000000000040",
		"zllywj": "0000000002016020100005.voc",
		"zlczwj": null,
		"zllrr": "zscj005",
		"zllrsj": "2016-02-01",
		"zllrdw": "知识库运维组",
		"zlzt": "99",
		"zlsfyx": "0",
		"zlsffb": "0",
		"zlfbr": "system",
		"zlly": null,
		"zlsz": "0",
		"zlwh": "财税〔2016〕11号",
		"zlfwdw": "财政部",
		"zlbfrq": 1454037700000,
		"zlsxrq": null,
		"zlssrq": 1454296900000,
		"zlwjdj": "3",
		"zlsydj": "0",
		"zlnowshr": null,
		"zlnowshjs": null,
		"zlnowjg": null,
		"zlnowbm": null,
		"zlzhczr": "zssh001",
		"zlzhczsj": 1454312972000,
		"lastczr": null,
		"zlqzz": null,
		"zlwxyy": null,
		"zlzy": null,
		"zlpz": null,
		"zlsfgk": "0",
		"zlfbrq": 1454312972000,
		"zlcxyy": "知识库清理。",
		"zlnzoa": null,
		"zloaid": null,
		"zldq": "00000000",
		"zldqmc": "中华人民共和国",
		"zlfwzg": null,
		"zlsfdl": "0",
		"zlsfzcyh": "0",
		"zldxlx": "00000000000000000000003",
		"zldqbbh": "0000000002016020100005002",
		"zldffg": null,
		"zlxf": null,
		"zlywczr": null,
		"zltypemc": "税收法规->其他地方规费",
		"zlhytypemc": "通用政策",
		"zlfz": 0,
		"zlisdel": "0",
		"zlwzfgbh": null,
		"zldxlxmc": "全部",
		"zlcxlcid": null,
		"gxsj": "2016-02-01 15:49:32",
		"bbh": null,
		"jhzt": "1",
		"xzqh": "000000000",
		"zlcxsqr": "zssh001",
		"zldlssid": "0",
		"zldlxh": null,
		"zlsxczbs": "0",
		"zlsfjs": "0",
		"zlsfzjsh": "0",
		"zlzgdw": null,
		"zlzgdwmc": null
	}, {
		"zlcode": "0000000002016020100003",
		"zlwfid": null,
		"activityid": null,
		"zljm": "41007",
		"zltitle": "财政部 国家税务总局关于扩大有关政府性基金免征范围的通知",
		"zlgjz": "教育费附加 地方教育附加 水利建设基金 销售额 营业额",
		"zlflag": "1",
		"zltype": "“1“000000000122“",
		"zlhytype": "00000000000000000000040",
		"zllywj": "0000000002016020100003.voc",
		"zlczwj": null,
		"zllrr": "zscj005",
		"zllrsj": "2016-02-01",
		"zllrdw": "知识库运维组",
		"zlzt": "60",
		"zlsfyx": "0",
		"zlsffb": "1",
		"zlfbr": "system",
		"zlly": null,
		"zlsz": "0",
		"zlwh": "财税〔2016〕12号",
		"zlfwdw": "财政部 国家税务总局",
		"zlbfrq": 1454037264000,
		"zlsxrq": null,
		"zlssrq": 1454296464000,
		"zlwjdj": "3",
		"zlsydj": "0",
		"zlnowshr": null,
		"zlnowshjs": null,
		"zlnowjg": null,
		"zlnowbm": null,
		"zlzhczr": "zssh001",
		"zlzhczsj": 1454296619000,
		"lastczr": null,
		"zlqzz": null,
		"zlwxyy": null,
		"zlzy": null,
		"zlpz": null,
		"zlsfgk": "0",
		"zlfbrq": 1454296619000,
		"zlcxyy": null,
		"zlnzoa": null,
		"zloaid": null,
		"zldq": "00000000",
		"zldqmc": "中华人民共和国",
		"zlfwzg": null,
		"zlsfdl": "0",
		"zlsfzcyh": "1",
		"zldxlx": "00000000000000000000003",
		"zldqbbh": "0000000002016020100003002",
		"zldffg": null,
		"zlxf": null,
		"zlywczr": null,
		"zltypemc": "税收法规->其他地方规费",
		"zlhytypemc": "通用政策",
		"zlfz": 687,
		"zlisdel": "0",
		"zlwzfgbh": null,
		"zldxlxmc": "全部",
		"zlcxlcid": null,
		"gxsj": "2016-02-01 11:16:59",
		"bbh": null,
		"jhzt": "1",
		"xzqh": "000000000",
		"zlcxsqr": null,
		"zldlssid": "0",
		"zldlxh": null,
		"zlsxczbs": "0",
		"zlsfjs": "0",
		"zlsfzjsh": "0",
		"zlzgdw": null,
		"zlzgdwmc": null
	}, {
		"zlcode": "1450000002016020100003",
		"zlwfid": null,
		"activityid": null,
		"zljm": "21031",
		"zltitle": "关于扩大有关政府性基金免征范围的通知",
		"zlgjz": "政府性基金 水利 地方教育",
		"zlflag": "1",
		"zltype": "“1“000000000122“",
		"zlhytype": "00000000000000000000040",
		"zllywj": "1450000002016020100003.voc",
		"zlczwj": null,
		"zllrr": "杨玲",
		"zllrsj": "2016-02-01",
		"zllrdw": "12366纳税服务热线",
		"zlzt": "99",
		"zlsfyx": "0",
		"zlsffb": "0",
		"zlfbr": "杨玲",
		"zlly": null,
		"zlsz": "1",
		"zlwh": "财税〔2016〕12号",
		"zlfwdw": "财政部 国家税务总局",
		"zlbfrq": 1454035450000,
		"zlsxrq": null,
		"zlssrq": null,
		"zlwjdj": "3",
		"zlsydj": "1",
		"zlnowshr": null,
		"zlnowshjs": null,
		"zlnowjg": null,
		"zlnowbm": null,
		"zlzhczr": "杨玲",
		"zlzhczsj": 1455843912000,
		"lastczr": null,
		"zlqzz": null,
		"zlwxyy": null,
		"zlzy": null,
		"zlpz": null,
		"zlsfgk": "0",
		"zlfbrq": 1455843912000,
		"zlcxyy": "重复",
		"zlnzoa": null,
		"zloaid": null,
		"zldq": "45000000",
		"zldqmc": "广西壮族自治区",
		"zlfwzg": null,
		"zlsfdl": "0",
		"zlsfzcyh": "0",
		"zldxlx": "00000000000000000000003",
		"zldqbbh": "1450000002016020100003002",
		"zldffg": null,
		"zlxf": null,
		"zlywczr": null,
		"zltypemc": "税收法规->其他地方规费",
		"zlhytypemc": "通用政策",
		"zlfz": 87,
		"zlisdel": "0",
		"zlwzfgbh": null,
		"zldxlxmc": "全部",
		"zlcxlcid": "8970003_pkg_zskcx_zskcxlc_wp1",
		"gxsj": "2016-02-19 09:05:12",
		"bbh": null,
		"jhzt": "1",
		"xzqh": "145000000",
		"zlcxsqr": "nnsj0426",
		"zldlssid": "0",
		"zldlxh": null,
		"zlsxczbs": "0",
		"zlsfjs": "0",
		"zlsfzjsh": "0",
		"zlzgdw": null,
		"zlzgdwmc": null
	}, {
		"zlcode": "1450000002016012000003",
		"zlwfid": null,
		"activityid": null,
		"zljm": "21019",
		"zltitle": "南宁市人民政府关于减免征收价格调节基金有关问题的通知",
		"zlgjz": "价格调节基金 南宁市",
		"zlflag": "1",
		"zltype": "“1“000000000122“14500000012201“",
		"zlhytype": "00000000000000000000040",
		"zllywj": "1450000002016012000003.voc",
		"zlczwj": null,
		"zllrr": "杨玲",
		"zllrsj": "2016-01-20",
		"zllrdw": "12366纳税服务热线",
		"zlzt": "60",
		"zlsfyx": "0",
		"zlsffb": "1",
		"zlfbr": "杨玲",
		"zlly": null,
		"zlsz": "1",
		"zlwh": "南府发〔2015〕32号",
		"zlfwdw": "南宁市人民政府",
		"zlbfrq": 1450756012000,
		"zlsxrq": null,
		"zlssrq": null,
		"zlwjdj": "3",
		"zlsydj": "1",
		"zlnowshr": null,
		"zlnowshjs": null,
		"zlnowjg": null,
		"zlnowbm": null,
		"zlzhczr": "杨玲",
		"zlzhczsj": 1453261579000,
		"lastczr": null,
		"zlqzz": null,
		"zlwxyy": null,
		"zlzy": null,
		"zlpz": null,
		"zlsfgk": "0",
		"zlfbrq": 1453261579000,
		"zlcxyy": null,
		"zlnzoa": null,
		"zloaid": null,
		"zldq": "45000000",
		"zldqmc": "广西壮族自治区",
		"zlfwzg": null,
		"zlsfdl": "0",
		"zlsfzcyh": "0",
		"zldxlx": "00000000000000000000003",
		"zldqbbh": "1450000002016012000003002",
		"zldffg": null,
		"zlxf": null,
		"zlywczr": null,
		"zltypemc": "税收法规->其他地方规费->价格调节基金",
		"zlhytypemc": "通用政策",
		"zlfz": 114,
		"zlisdel": "0",
		"zlwzfgbh": null,
		"zldxlxmc": "全部",
		"zlcxlcid": null,
		"gxsj": null,
		"bbh": null,
		"jhzt": "1",
		"xzqh": "145000000",
		"zlcxsqr": null,
		"zldlssid": "0",
		"zldlxh": null,
		"zlsxczbs": "0",
		"zlsfjs": "0",
		"zlsfzjsh": "0",
		"zlzgdw": null,
		"zlzgdwmc": null
	}, {
		"zlcode": "0000000002016011100002",
		"zlwfid": null,
		"activityid": null,
		"zljm": "40849",
		"zltitle": "国家税务总局关于发布《社会保险费及其他基金规费文书式样》的公告",
		"zlgjz": "社会保险费 基金规费 文书 式样",
		"zlflag": "1",
		"zltype": "“1“000000000122“,“1“000000000121“",
		"zlhytype": "00000000000000000000040",
		"zllywj": "0000000002016011100002.voc",
		"zlczwj": null,
		"zllrr": "zscj005",
		"zllrsj": "2016-01-11",
		"zllrdw": "知识库运维组",
		"zlzt": "60",
		"zlsfyx": "0",
		"zlsffb": "1",
		"zlfbr": "system",
		"zlly": null,
		"zlsz": "0",
		"zlwh": "国家税务总局公告2015年第98号",
		"zlfwdw": "国家税务总局",
		"zlbfrq": 1451493471000,
		"zlsxrq": null,
		"zlssrq": 1451493471000,
		"zlwjdj": "3",
		"zlsydj": "0",
		"zlnowshr": null,
		"zlnowshjs": null,
		"zlnowjg": null,
		"zlnowbm": null,
		"zlzhczr": "zssh001",
		"zlzhczsj": 1452487328000,
		"lastczr": null,
		"zlqzz": null,
		"zlwxyy": null,
		"zlzy": null,
		"zlpz": null,
		"zlsfgk": "0",
		"zlfbrq": 1452487328000,
		"zlcxyy": null,
		"zlnzoa": null,
		"zloaid": null,
		"zldq": "00000000",
		"zldqmc": "中华人民共和国",
		"zlfwzg": null,
		"zlsfdl": "0",
		"zlsfzcyh": "0",
		"zldxlx": "00000000000000000000003",
		"zldqbbh": "0000000002016011100002003",
		"zldffg": null,
		"zlxf": null,
		"zlywczr": null,
		"zltypemc": "税收法规->社保费；税收法规->其他地方规费",
		"zlhytypemc": "通用政策",
		"zlfz": 5,
		"zlisdel": "0",
		"zlwzfgbh": null,
		"zldxlxmc": "全部",
		"zlcxlcid": null,
		"gxsj": "2016-01-11 12:42:08",
		"bbh": null,
		"jhzt": "1",
		"xzqh": "000000000",
		"zlcxsqr": null,
		"zldlssid": "0",
		"zldlxh": null,
		"zlsxczbs": "0",
		"zlsfjs": "0",
		"zlsfzjsh": "0",
		"zlzgdw": null,
		"zlzgdwmc": null
	}, {
		"zlcode": "0000000002015112300001",
		"zlwfid": null,
		"activityid": null,
		"zljm": "40517",
		"zltitle": "财政部 国家林业局关于调整森林植被恢复费征收标准引导节约集约利用林地的通知",
		"zlgjz": "森林植被恢复费 林地",
		"zlflag": "1",
		"zltype": "“1“000000000122“",
		"zlhytype": "00000000000000000000040",
		"zllywj": "0000000002015112300001.voc",
		"zlczwj": null,
		"zllrr": "zscj009",
		"zllrsj": "2015-11-23",
		"zllrdw": "知识库运维组",
		"zlzt": "99",
		"zlsfyx": "0",
		"zlsffb": "0",
		"zlfbr": "system",
		"zlly": null,
		"zlsz": "0",
		"zlwh": "财税〔2015〕122号",
		"zlfwdw": "财政部 国家林业局",
		"zlbfrq": 1447835896000,
		"zlsxrq": null,
		"zlssrq": 1447835896000,
		"zlwjdj": "3",
		"zlsydj": "0",
		"zlnowshr": null,
		"zlnowshjs": null,
		"zlnowjg": null,
		"zlnowbm": null,
		"zlzhczr": "zssh001",
		"zlzhczsj": 1450143935000,
		"lastczr": null,
		"zlqzz": null,
		"zlwxyy": null,
		"zlzy": null,
		"zlpz": null,
		"zlsfgk": "0",
		"zlfbrq": 1450143935000,
		"zlcxyy": "知识库清理。",
		"zlnzoa": null,
		"zloaid": null,
		"zldq": "00000000",
		"zldqmc": "中华人民共和国",
		"zlfwzg": null,
		"zlsfdl": "0",
		"zlsfzcyh": "0",
		"zldxlx": "00000000000000000000003",
		"zldqbbh": "0000000002015112300001002",
		"zldffg": null,
		"zlxf": null,
		"zlywczr": null,
		"zltypemc": "税收法规->其他地方规费",
		"zlhytypemc": "通用政策",
		"zlfz": 0,
		"zlisdel": "0",
		"zlwzfgbh": null,
		"zldxlxmc": "全部",
		"zlcxlcid": null,
		"gxsj": "2015-12-15 09:45:35",
		"bbh": null,
		"jhzt": "1",
		"xzqh": "000000000",
		"zlcxsqr": "zssh001",
		"zldlssid": "0",
		"zldlxh": null,
		"zlsxczbs": "0",
		"zlsfjs": "0",
		"zlsfzjsh": "0",
		"zlzgdw": null,
		"zlzgdwmc": null
	}, {
		"zlcode": "0000000002015111200003",
		"zlwfid": null,
		"activityid": null,
		"zljm": "40464",
		"zltitle": "废弃电器电子产品处理目录（2014年版）",
		"zlgjz": "废弃电器电子产品",
		"zlflag": "1",
		"zltype": "“1“000000000122“",
		"zlhytype": "00000000000000000000040",
		"zllywj": "0000000002015111200003.voc",
		"zlczwj": null,
		"zllrr": "zscj009",
		"zllrsj": "2015-11-12",
		"zllrdw": "知识库运维组",
		"zlzt": "60",
		"zlsfyx": "0",
		"zlsffb": "1",
		"zlfbr": "system",
		"zlly": null,
		"zlsz": "0",
		"zlwh": "国家发展和改革委员会 环境保护部 工业和信息化部 财政部 海关总署 国家税务总局公告2015年第5号",
		"zlfwdw": "国家发展和改革委员会 环境保护部 工业和信息化部 财政部 海关总署 国家税务总局",
		"zlbfrq": 1423451859000,
		"zlsxrq": null,
		"zlssrq": 1456802259000,
		"zlwjdj": "3",
		"zlsydj": "0",
		"zlnowshr": null,
		"zlnowshjs": null,
		"zlnowjg": null,
		"zlnowbm": null,
		"zlzhczr": "zssh001",
		"zlzhczsj": 1447298567000,
		"lastczr": null,
		"zlqzz": null,
		"zlwxyy": null,
		"zlzy": null,
		"zlpz": null,
		"zlsfgk": "0",
		"zlfbrq": 1447298567000,
		"zlcxyy": null,
		"zlnzoa": null,
		"zloaid": null,
		"zldq": "00000000",
		"zldqmc": "中华人民共和国",
		"zlfwzg": null,
		"zlsfdl": "0",
		"zlsfzcyh": "0",
		"zldxlx": "00000000000000000000003",
		"zldqbbh": "0000000002015111200003002",
		"zldffg": null,
		"zlxf": null,
		"zlywczr": null,
		"zltypemc": "税收法规->其他地方规费",
		"zlhytypemc": "通用政策",
		"zlfz": 26,
		"zlisdel": "0",
		"zlwzfgbh": null,
		"zldxlxmc": "全部",
		"zlcxlcid": null,
		"gxsj": "2015-11-12 11:22:47",
		"bbh": null,
		"jhzt": "1",
		"xzqh": "000000000",
		"zlcxsqr": null,
		"zldlssid": "0",
		"zldlxh": null,
		"zlsxczbs": "0",
		"zlsfjs": "0",
		"zlsfzjsh": "0",
		"zlzgdw": null,
		"zlzgdwmc": null
	}, {
		"zlcode": "0000000002015103000004",
		"zlwfid": null,
		"activityid": null,
		"zljm": "40335",
		"zltitle": "关于印发《污水处理费征收使用管理办法》的通知",
		"zlgjz": "行政事业性收费 污水处理费",
		"zlflag": "1",
		"zltype": "“1“000000000122“",
		"zlhytype": "00000000000000000000040",
		"zllywj": "0000000002015103000004.voc",
		"zlczwj": null,
		"zllrr": "zscj009",
		"zllrsj": "2015-10-30",
		"zllrdw": "知识库运维组",
		"zlzt": "60",
		"zlsfyx": "0",
		"zlsffb": "1",
		"zlfbr": "system",
		"zlly": null,
		"zlsz": "0",
		"zlwh": "财税〔2014〕151号",
		"zlfwdw": "财政部 国家发展改革委 住房城乡建设部",
		"zlbfrq": 1420011666000,
		"zlsxrq": null,
		"zlssrq": 1425195666000,
		"zlwjdj": "3",
		"zlsydj": "0",
		"zlnowshr": null,
		"zlnowshjs": null,
		"zlnowjg": null,
		"zlnowbm": null,
		"zlzhczr": "zssh001",
		"zlzhczsj": 1446191556000,
		"lastczr": null,
		"zlqzz": null,
		"zlwxyy": null,
		"zlzy": null,
		"zlpz": null,
		"zlsfgk": "0",
		"zlfbrq": 1446191556000,
		"zlcxyy": null,
		"zlnzoa": null,
		"zloaid": null,
		"zldq": "00000000",
		"zldqmc": "中华人民共和国",
		"zlfwzg": null,
		"zlsfdl": "0",
		"zlsfzcyh": "0",
		"zldxlx": "00000000000000000000003",
		"zldqbbh": "0000000002015103000004002",
		"zldffg": null,
		"zlxf": null,
		"zlywczr": null,
		"zltypemc": "税收法规->其他地方规费",
		"zlhytypemc": "通用政策",
		"zlfz": 67,
		"zlisdel": "0",
		"zlwzfgbh": null,
		"zldxlxmc": "全部",
		"zlcxlcid": null,
		"gxsj": "2015-10-30 15:52:36",
		"bbh": null,
		"jhzt": "1",
		"xzqh": "000000000",
		"zlcxsqr": null,
		"zldlssid": "0",
		"zldlxh": null,
		"zlsxczbs": "0",
		"zlsfjs": "0",
		"zlsfzjsh": "0",
		"zlzgdw": null,
		"zlzgdwmc": null
	}, {
		"zlcode": "0000000002015101300001",
		"zlwfid": null,
		"activityid": null,
		"zljm": "40262",
		"zltitle": "财政部 国家发展改革委关于取消和暂停征收一批行政事业性收费有关问题的通知",
		"zlgjz": "行政事业性收费 ",
		"zlflag": "1",
		"zltype": "“1“000000000122“",
		"zlhytype": "00000000000000000000040",
		"zllywj": "0000000002015101300001.voc",
		"zlczwj": null,
		"zllrr": "zscj009",
		"zllrsj": "2015-10-13",
		"zllrdw": "知识库运维组",
		"zlzt": "60",
		"zlsfyx": "0",
		"zlsffb": "1",
		"zlfbr": "system",
		"zlly": null,
		"zlsz": "0",
		"zlwh": "财税〔2015〕102号",
		"zlfwdw": "财政部 国家发展改革委",
		"zlbfrq": 1443495256000,
		"zlsxrq": null,
		"zlssrq": 1443495256000,
		"zlwjdj": "3",
		"zlsydj": "0",
		"zlnowshr": null,
		"zlnowshjs": null,
		"zlnowjg": null,
		"zlnowbm": null,
		"zlzhczr": "zssh001",
		"zlzhczsj": 1444706285000,
		"lastczr": null,
		"zlqzz": null,
		"zlwxyy": null,
		"zlzy": null,
		"zlpz": null,
		"zlsfgk": "0",
		"zlfbrq": 1444706285000,
		"zlcxyy": null,
		"zlnzoa": null,
		"zloaid": null,
		"zldq": "00000000",
		"zldqmc": "中华人民共和国",
		"zlfwzg": null,
		"zlsfdl": "0",
		"zlsfzcyh": "0",
		"zldxlx": "00000000000000000000003",
		"zldqbbh": "0000000002015101300001002",
		"zldffg": null,
		"zlxf": null,
		"zlywczr": null,
		"zltypemc": "税收法规->其他地方规费",
		"zlhytypemc": "通用政策",
		"zlfz": 4,
		"zlisdel": "0",
		"zlwzfgbh": null,
		"zldxlxmc": "全部",
		"zlcxlcid": null,
		"gxsj": "2015-10-13 11:18:05",
		"bbh": null,
		"jhzt": "1",
		"xzqh": "000000000",
		"zlcxsqr": null,
		"zldlssid": "0",
		"zldlxh": null,
		"zlsxczbs": "0",
		"zlsfjs": "0",
		"zlsfzjsh": "0",
		"zlzgdw": null,
		"zlzgdwmc": null
	}, {
		"zlcode": "0000000002015092800003",
		"zlwfid": null,
		"activityid": null,
		"zljm": "40181",
		"zltitle": "财政部 国家发展改革委关于重新发布中央管理的住房城乡建设部门行政事业性收费项目的通知",
		"zlgjz": "行政事业性收费 ",
		"zlflag": "1",
		"zltype": "“1“000000000122“",
		"zlhytype": "00000000000000000000040",
		"zllywj": "0000000002015092800003.voc",
		"zlczwj": null,
		"zllrr": "zscj009",
		"zllrsj": "2015-09-28",
		"zllrdw": "知识库运维组",
		"zlzt": "60",
		"zlsfyx": "0",
		"zlsffb": "1",
		"zlfbr": "system",
		"zlly": null,
		"zlsz": "0",
		"zlwh": "财税〔2015〕68号",
		"zlfwdw": "财政部 国家发展改革委",
		"zlbfrq": 1441691627000,
		"zlsxrq": null,
		"zlssrq": 1441691627000,
		"zlwjdj": "3",
		"zlsydj": "0",
		"zlnowshr": null,
		"zlnowshjs": null,
		"zlnowjg": null,
		"zlnowbm": null,
		"zlzhczr": "zssh001",
		"zlzhczsj": 1443419947000,
		"lastczr": null,
		"zlqzz": null,
		"zlwxyy": null,
		"zlzy": null,
		"zlpz": null,
		"zlsfgk": "0",
		"zlfbrq": 1443419947000,
		"zlcxyy": null,
		"zlnzoa": null,
		"zloaid": null,
		"zldq": "00000000",
		"zldqmc": "中华人民共和国",
		"zlfwzg": null,
		"zlsfdl": "0",
		"zlsfzcyh": "0",
		"zldxlx": "00000000000000000000003",
		"zldqbbh": "0000000002015092800003002",
		"zldffg": null,
		"zlxf": null,
		"zlywczr": null,
		"zltypemc": "税收法规->其他地方规费",
		"zlhytypemc": "通用政策",
		"zlfz": 3,
		"zlisdel": "0",
		"zlwzfgbh": null,
		"zldxlxmc": "全部",
		"zlcxlcid": null,
		"gxsj": "2015-09-28 13:59:07",
		"bbh": null,
		"jhzt": "1",
		"xzqh": "000000000",
		"zlcxsqr": null,
		"zldlssid": "0",
		"zldlxh": null,
		"zlsxczbs": "0",
		"zlsfjs": "0",
		"zlsfzjsh": "1",
		"zlzgdw": null,
		"zlzgdwmc": null
	}, {
		"zlcode": "0000000002015091800009",
		"zlwfid": null,
		"activityid": null,
		"zljm": "40124",
		"zltitle": "国家税务总局关于修订《废弃电器电子产品处理基金申报表》的公告",
		"zlgjz": "废弃电器电子产品处理基金申报表 ",
		"zlflag": "1",
		"zltype": "“1“000000000122“",
		"zlhytype": "00000000000000000000040",
		"zllywj": "0000000002015091800009.voc",
		"zlczwj": null,
		"zllrr": "zscj009",
		"zllrsj": "2015-09-23",
		"zllrdw": "知识库运维组",
		"zlzt": "60",
		"zlsfyx": "0",
		"zlsffb": "1",
		"zlfbr": "system",
		"zlly": null,
		"zlsz": "0",
		"zlwh": "国家税务总局公告2015年第62号",
		"zlfwdw": "国家税务总局",
		"zlbfrq": 1442217723000,
		"zlsxrq": null,
		"zlssrq": 1456819323000,
		"zlwjdj": "3",
		"zlsydj": "0",
		"zlnowshr": null,
		"zlnowshjs": null,
		"zlnowjg": null,
		"zlnowbm": null,
		"zlzhczr": "zssh001",
		"zlzhczsj": 1442996122000,
		"lastczr": null,
		"zlqzz": null,
		"zlwxyy": null,
		"zlzy": null,
		"zlpz": null,
		"zlsfgk": "0",
		"zlfbrq": 1442996122000,
		"zlcxyy": null,
		"zlnzoa": null,
		"zloaid": null,
		"zldq": "00000000",
		"zldqmc": "中华人民共和国",
		"zlfwzg": null,
		"zlsfdl": "0",
		"zlsfzcyh": "0",
		"zldxlx": "00000000000000000000003",
		"zldqbbh": "0000000002015091800009003",
		"zldffg": null,
		"zlxf": null,
		"zlywczr": null,
		"zltypemc": "税收法规->其他地方规费",
		"zlhytypemc": "通用政策",
		"zlfz": 20,
		"zlisdel": "0",
		"zlwzfgbh": null,
		"zldxlxmc": "全部",
		"zlcxlcid": null,
		"gxsj": "2015-09-23 16:15:22",
		"bbh": null,
		"jhzt": "1",
		"xzqh": "000000000",
		"zlcxsqr": null,
		"zldlssid": "0",
		"zldlxh": null,
		"zlsxczbs": "0",
		"zlsfjs": "0",
		"zlsfzjsh": "1",
		"zlzgdw": null,
		"zlzgdwmc": null
	}, {
		"zlcode": "0000000002015091600001",
		"zlwfid": null,
		"activityid": null,
		"zljm": "40103",
		"zltitle": "财政部 国家税务总局 中国残疾人联合会关于印发《残疾人就业保障金征收使用管理办法》的通知",
		"zlgjz": "残疾人就业保障金 促进残疾人就业",
		"zlflag": "1",
		"zltype": "“1“000000000122“",
		"zlhytype": "00000000000000000000040",
		"zllywj": "0000000002015091600001.voc",
		"zlczwj": null,
		"zllrr": "zscj009",
		"zllrsj": "2015-09-16",
		"zllrdw": "知识库运维组",
		"zlzt": "60",
		"zlsfyx": "0",
		"zlsffb": "1",
		"zlfbr": "system",
		"zlly": null,
		"zlsz": "0",
		"zlwh": "财税〔2015〕72号",
		"zlfwdw": "财政部 国家税务总局 中国残疾人联合会",
		"zlbfrq": 1441779313000,
		"zlsxrq": null,
		"zlssrq": 1443680113000,
		"zlwjdj": "3",
		"zlsydj": "0",
		"zlnowshr": null,
		"zlnowshjs": null,
		"zlnowjg": null,
		"zlnowbm": null,
		"zlzhczr": "zssh001",
		"zlzhczsj": 1442384447000,
		"lastczr": null,
		"zlqzz": null,
		"zlwxyy": null,
		"zlzy": null,
		"zlpz": null,
		"zlsfgk": "0",
		"zlfbrq": 1442384447000,
		"zlcxyy": null,
		"zlnzoa": null,
		"zloaid": null,
		"zldq": "00000000",
		"zldqmc": "中华人民共和国",
		"zlfwzg": null,
		"zlsfdl": "0",
		"zlsfzcyh": "0",
		"zldxlx": "00000000000000000000003",
		"zldqbbh": "0000000002015091600001002",
		"zldffg": null,
		"zlxf": null,
		"zlywczr": null,
		"zltypemc": "税收法规->其他地方规费",
		"zlhytypemc": "通用政策",
		"zlfz": 24,
		"zlisdel": "0",
		"zlwzfgbh": null,
		"zldxlxmc": "全部",
		"zlcxlcid": null,
		"gxsj": "2015-09-16 14:20:47",
		"bbh": null,
		"jhzt": "1",
		"xzqh": "000000000",
		"zlcxsqr": null,
		"zldlssid": "0",
		"zldlxh": null,
		"zlsxczbs": "0",
		"zlsfjs": "0",
		"zlsfzjsh": "1",
		"zlzgdw": null,
		"zlzgdwmc": null
	}, {
		"zlcode": "0000000002015090900001",
		"zlwfid": null,
		"activityid": null,
		"zljm": "40067",
		"zltitle": "财政部 国家新闻出版广电总局关于印发《国家电影事业发展专项资金征收使用管理办法》的通知",
		"zlgjz": "国家电影事业发展专项资金 征收 使用 管理",
		"zlflag": "1",
		"zltype": "“1“000000000122“",
		"zlhytype": "00000000000000000000040",
		"zllywj": "0000000002015090900001.voc",
		"zlczwj": null,
		"zllrr": "zscj009",
		"zllrsj": "2015-09-09",
		"zllrdw": "知识库运维组",
		"zlzt": "60",
		"zlsfyx": "0",
		"zlsffb": "1",
		"zlfbr": "system",
		"zlly": null,
		"zlsz": "0",
		"zlwh": "财税〔2015〕91号",
		"zlfwdw": "财政部 国家新闻出版广电总局",
		"zlbfrq": 1441005803000,
		"zlsxrq": null,
		"zlssrq": 1443684203000,
		"zlwjdj": "3",
		"zlsydj": "0",
		"zlnowshr": null,
		"zlnowshjs": null,
		"zlnowjg": null,
		"zlnowbm": null,
		"zlzhczr": "zssh001",
		"zlzhczsj": 1441784507000,
		"lastczr": null,
		"zlqzz": null,
		"zlwxyy": null,
		"zlzy": null,
		"zlpz": null,
		"zlsfgk": "0",
		"zlfbrq": 1441784507000,
		"zlcxyy": null,
		"zlnzoa": null,
		"zloaid": null,
		"zldq": "00000000",
		"zldqmc": "中华人民共和国",
		"zlfwzg": null,
		"zlsfdl": "0",
		"zlsfzcyh": "0",
		"zldxlx": "00000000000000000000003",
		"zldqbbh": "0000000002015090900001002",
		"zldffg": null,
		"zlxf": null,
		"zlywczr": null,
		"zltypemc": "税收法规->其他地方规费",
		"zlhytypemc": "通用政策",
		"zlfz": 19,
		"zlisdel": "0",
		"zlwzfgbh": null,
		"zldxlxmc": "全部",
		"zlcxlcid": null,
		"gxsj": "2015-09-09 15:41:47",
		"bbh": null,
		"jhzt": "1",
		"xzqh": "000000000",
		"zlcxsqr": null,
		"zldlssid": "0",
		"zldlxh": null,
		"zlsxczbs": "0",
		"zlsfjs": "0",
		"zlsfzjsh": "1",
		"zlzgdw": null,
		"zlzgdwmc": null
	}, {
		"zlcode": "0000000002015082500005",
		"zlwfid": null,
		"activityid": null,
		"zljm": "40007",
		"zltitle": "财政部 国家发展改革委关于取消有关水运涉企行政事业性收费项目的通知",
		"zlgjz": "行政事业性收费 水运涉企 长江经济带",
		"zlflag": "1",
		"zltype": "“1“000000000122“",
		"zlhytype": "00000000000000000000040",
		"zllywj": "0000000002015082500005.voc",
		"zlczwj": null,
		"zllrr": "zscj009",
		"zllrsj": "2015-08-25",
		"zllrdw": "知识库运维组",
		"zlzt": "60",
		"zlsfyx": "0",
		"zlsffb": "1",
		"zlfbr": "system",
		"zlly": null,
		"zlsz": "0",
		"zlwh": "财税〔2015〕92号",
		"zlfwdw": "财政部 国家发展改革委",
		"zlbfrq": 1439797983000,
		"zlsxrq": null,
		"zlssrq": 1443685983000,
		"zlwjdj": "3",
		"zlsydj": "0",
		"zlnowshr": null,
		"zlnowshjs": null,
		"zlnowjg": null,
		"zlnowbm": null,
		"zlzhczr": "zssh001",
		"zlzhczsj": 1440489741000,
		"lastczr": null,
		"zlqzz": null,
		"zlwxyy": null,
		"zlzy": null,
		"zlpz": null,
		"zlsfgk": "0",
		"zlfbrq": 1440489741000,
		"zlcxyy": null,
		"zlnzoa": null,
		"zloaid": null,
		"zldq": "00000000",
		"zldqmc": "中华人民共和国",
		"zlfwzg": null,
		"zlsfdl": "0",
		"zlsfzcyh": "0",
		"zldxlx": "00000000000000000000003",
		"zldqbbh": "0000000002015082500005002",
		"zldffg": null,
		"zlxf": null,
		"zlywczr": null,
		"zltypemc": "税收法规->其他地方规费",
		"zlhytypemc": "通用政策",
		"zlfz": 15,
		"zlisdel": "0",
		"zlwzfgbh": null,
		"zldxlxmc": "全部",
		"zlcxlcid": null,
		"gxsj": "2015-08-25 16:02:21",
		"bbh": null,
		"jhzt": "1",
		"xzqh": "000000000",
		"zlcxsqr": null,
		"zldlssid": "0",
		"zldlxh": null,
		"zlsxczbs": "0",
		"zlsfjs": "0",
		"zlsfzjsh": "0",
		"zlzgdw": null,
		"zlzgdwmc": null
	}, {
		"zlcode": "0000000002015082000007",
		"zlwfid": null,
		"activityid": null,
		"zljm": "39918",
		"zltitle": "财政部 国家发展改革委关于发布国家铁路局行政事业性收费项目的通知",
		"zlgjz": "铁路 行政事业性收费 收费项目 ",
		"zlflag": "1",
		"zltype": "“1“000000000122“",
		"zlhytype": "00000000000000000000040",
		"zllywj": "0000000002015082000007.voc",
		"zlczwj": null,
		"zllrr": "zscj009",
		"zllrsj": "2015-08-20",
		"zllrdw": "知识库运维组",
		"zlzt": "60",
		"zlsfyx": "0",
		"zlsffb": "1",
		"zlfbr": "system",
		"zlly": null,
		"zlsz": "0",
		"zlwh": "财税〔2015〕75号",
		"zlfwdw": "财政部 国家发展改革委",
		"zlbfrq": 1438222589000,
		"zlsxrq": null,
		"zlssrq": 1438222589000,
		"zlwjdj": "3",
		"zlsydj": "0",
		"zlnowshr": null,
		"zlnowshjs": null,
		"zlnowjg": null,
		"zlnowbm": null,
		"zlzhczr": "zssh001",
		"zlzhczsj": 1440128092000,
		"lastczr": null,
		"zlqzz": null,
		"zlwxyy": null,
		"zlzy": null,
		"zlpz": null,
		"zlsfgk": "0",
		"zlfbrq": 1440128092000,
		"zlcxyy": null,
		"zlnzoa": null,
		"zloaid": null,
		"zldq": "00000000",
		"zldqmc": "中华人民共和国",
		"zlfwzg": null,
		"zlsfdl": "0",
		"zlsfzcyh": "0",
		"zldxlx": "00000000000000000000003",
		"zldqbbh": "0000000002015082000007002",
		"zldffg": null,
		"zlxf": null,
		"zlywczr": null,
		"zltypemc": "税收法规->其他地方规费",
		"zlhytypemc": "通用政策",
		"zlfz": 7,
		"zlisdel": "0",
		"zlwzfgbh": null,
		"zldxlxmc": "全部",
		"zlcxlcid": null,
		"gxsj": "2015-08-21 11:34:52",
		"bbh": null,
		"jhzt": "1",
		"xzqh": "000000000",
		"zlcxsqr": null,
		"zldlssid": "0",
		"zldlxh": null,
		"zlsxczbs": "0",
		"zlsfjs": "0",
		"zlsfzjsh": "0",
		"zlzgdw": null,
		"zlzgdwmc": null
	}, {
		"zlcode": "0000000002015080300067",
		"zlwfid": null,
		"activityid": null,
		"zljm": "39483",
		"zltitle": "财政部 国家发展改革委关于重新发布中央管理的人力资源社会保障部门行政事业性收费项目的通知",
		"zlgjz": "行政事业性收费 专业技术人员职业资格考试",
		"zlflag": "1",
		"zltype": "“1“000000000122“",
		"zlhytype": "00000000000000000000040",
		"zllywj": "0000000002015080300067.voc",
		"zlczwj": null,
		"zllrr": "zscj009",
		"zllrsj": "2015-08-03",
		"zllrdw": "知识库运维组",
		"zlzt": "60",
		"zlsfyx": "0",
		"zlsffb": "1",
		"zlfbr": "system",
		"zlly": null,
		"zlsz": "0",
		"zlwh": "财税〔2015〕69号",
		"zlfwdw": "财政部 国家发展改革委",
		"zlbfrq": 1437373295000,
		"zlsxrq": null,
		"zlssrq": 1437373295000,
		"zlwjdj": "3",
		"zlsydj": "0",
		"zlnowshr": null,
		"zlnowshjs": null,
		"zlnowjg": null,
		"zlnowbm": null,
		"zlzhczr": "zssh001",
		"zlzhczsj": 1438583179000,
		"lastczr": null,
		"zlqzz": null,
		"zlwxyy": null,
		"zlzy": null,
		"zlpz": null,
		"zlsfgk": "0",
		"zlfbrq": 1438583179000,
		"zlcxyy": null,
		"zlnzoa": null,
		"zloaid": null,
		"zldq": "00000000",
		"zldqmc": "中华人民共和国",
		"zlfwzg": null,
		"zlsfdl": "0",
		"zlsfzcyh": "0",
		"zldxlx": "00000000000000000000003",
		"zldqbbh": "0000000002015080300067002",
		"zldffg": null,
		"zlxf": null,
		"zlywczr": null,
		"zltypemc": "税收法规->其他地方规费",
		"zlhytypemc": "通用政策",
		"zlfz": 5,
		"zlisdel": "0",
		"zlwzfgbh": null,
		"zldxlxmc": "全部",
		"zlcxlcid": null,
		"gxsj": "2015-08-03 14:26:19",
		"bbh": null,
		"jhzt": "1",
		"xzqh": "000000000",
		"zlcxsqr": null,
		"zldlssid": "0",
		"zldlxh": null,
		"zlsxczbs": "0",
		"zlsfjs": "0",
		"zlsfzjsh": "0",
		"zlzgdw": null,
		"zlzgdwmc": null
	}, {
		"zlcode": "0000000002015080300064",
		"zlwfid": null,
		"activityid": null,
		"zljm": "39480",
		"zltitle": "财政部 国家发展改革委 环境保护部关于印发《排污权出让收入管理暂行办法》的通知",
		"zlgjz": "环境保护 排污权出让收入 排污权使用费",
		"zlflag": "1",
		"zltype": "“1“000000000122“",
		"zlhytype": "00000000000000000000040",
		"zllywj": "0000000002015080300064.voc",
		"zlczwj": null,
		"zllrr": "zscj009",
		"zllrsj": "2015-08-03",
		"zllrdw": "知识库运维组",
		"zlzt": "60",
		"zlsfyx": "0",
		"zlsffb": "1",
		"zlfbr": "system",
		"zlly": null,
		"zlsz": "0",
		"zlwh": "财税〔2015〕61号",
		"zlfwdw": "财政部 国家发展改革委 环境保护部",
		"zlbfrq": 1437631239000,
		"zlsxrq": null,
		"zlssrq": 1443679239000,
		"zlwjdj": "3",
		"zlsydj": "0",
		"zlnowshr": null,
		"zlnowshjs": null,
		"zlnowjg": null,
		"zlnowbm": null,
		"zlzhczr": "zssh001",
		"zlzhczsj": 1438582537000,
		"lastczr": null,
		"zlqzz": null,
		"zlwxyy": null,
		"zlzy": null,
		"zlpz": null,
		"zlsfgk": "0",
		"zlfbrq": 1438582537000,
		"zlcxyy": null,
		"zlnzoa": null,
		"zloaid": null,
		"zldq": "00000000",
		"zldqmc": "中华人民共和国",
		"zlfwzg": null,
		"zlsfdl": "0",
		"zlsfzcyh": "0",
		"zldxlx": "00000000000000000000003",
		"zldqbbh": "0000000002015080300064002",
		"zldffg": null,
		"zlxf": null,
		"zlywczr": null,
		"zltypemc": "税收法规->其他地方规费",
		"zlhytypemc": "通用政策",
		"zlfz": 7,
		"zlisdel": "0",
		"zlwzfgbh": null,
		"zldxlxmc": "全部",
		"zlcxlcid": null,
		"gxsj": "2015-08-03 14:15:37",
		"bbh": null,
		"jhzt": "1",
		"xzqh": "000000000",
		"zlcxsqr": null,
		"zldlssid": "0",
		"zldlxh": null,
		"zlsxczbs": "0",
		"zlsfjs": "0",
		"zlsfzjsh": "0",
		"zlzgdw": null,
		"zlzgdwmc": null
	}, {
		"zlcode": "1450000002015052800001",
		"zlwfid": null,
		"activityid": null,
		"zljm": "20902",
		"zltitle": "广西壮族自治区物价局关于暂停征收临时电力价格调节基金的通知",
		"zlgjz": "临时电力 价格调节基金",
		"zlflag": "1",
		"zltype": "“1“000000000122“14500000012201“",
		"zlhytype": "00000000000000000000040",
		"zllywj": "1450000002015052800001.voc",
		"zlczwj": null,
		"zllrr": "广西国税管理员",
		"zllrsj": "2015-05-28",
		"zllrdw": "广西壮族自治区国家税务局",
		"zlzt": "60",
		"zlsfyx": "0",
		"zlsffb": "1",
		"zlfbr": "广西国税管理员",
		"zlly": null,
		"zlsz": "1",
		"zlwh": "桂价调〔2015〕46号",
		"zlfwdw": "广西壮族自治区物价局",
		"zlbfrq": 1430301152000,
		"zlsxrq": null,
		"zlssrq": null,
		"zlwjdj": "3",
		"zlsydj": "1",
		"zlnowshr": null,
		"zlnowshjs": null,
		"zlnowjg": null,
		"zlnowbm": null,
		"zlzhczr": "广西国税管理员",
		"zlzhczsj": 1432806037000,
		"lastczr": null,
		"zlqzz": null,
		"zlwxyy": null,
		"zlzy": null,
		"zlpz": null,
		"zlsfgk": "0",
		"zlfbrq": 1432806037000,
		"zlcxyy": null,
		"zlnzoa": null,
		"zloaid": null,
		"zldq": "45000000",
		"zldqmc": "广西壮族自治区",
		"zlfwzg": null,
		"zlsfdl": "0",
		"zlsfzcyh": "0",
		"zldxlx": "00000000000000000000003",
		"zldqbbh": "1450000002015052800001002",
		"zldffg": null,
		"zlxf": null,
		"zlywczr": null,
		"zltypemc": "税收法规->其他地方规费->价格调节基金",
		"zlhytypemc": "通用政策",
		"zlfz": 40,
		"zlisdel": "0",
		"zlwzfgbh": null,
		"zldxlxmc": "全部",
		"zlcxlcid": null,
		"gxsj": null,
		"bbh": null,
		"jhzt": "1",
		"xzqh": "145000000",
		"zlcxsqr": null,
		"zldlssid": "0",
		"zldlxh": null,
		"zlsxczbs": "0",
		"zlsfjs": "0",
		"zlsfzjsh": "0",
		"zlzgdw": null,
		"zlzgdwmc": null
	}, {
		"zlcode": "0000000002015050700007",
		"zlwfid": null,
		"activityid": null,
		"zljm": "38158",
		"zltitle": "财政部 国家发展改革委关于重新发布中央管理的食品药品监督管理部门行政事业性收费项目的通知",
		"zlgjz": "药品 医疗器械 行政事业性收费",
		"zlflag": "1",
		"zltype": "“1“000000000122“",
		"zlhytype": "00000000000000000000040",
		"zllywj": "0000000002015050700007.voc",
		"zlczwj": null,
		"zllrr": "ssfgcj001",
		"zllrsj": "2015-05-07",
		"zllrdw": "第七运维中心",
		"zlzt": "60",
		"zlsfyx": "0",
		"zlsffb": "1",
		"zlfbr": "system",
		"zlly": null,
		"zlsz": "0",
		"zlwh": "财税〔2015〕2号",
		"zlfwdw": "财政部 国家发展改革委",
		"zlbfrq": 1429601730000,
		"zlsxrq": null,
		"zlssrq": 1429601730000,
		"zlwjdj": "3",
		"zlsydj": "0",
		"zlnowshr": null,
		"zlnowshjs": null,
		"zlnowjg": null,
		"zlnowbm": null,
		"zlzhczr": "ssfgsh001",
		"zlzhczsj": 1430984415000,
		"lastczr": null,
		"zlqzz": null,
		"zlwxyy": null,
		"zlzy": null,
		"zlpz": null,
		"zlsfgk": "0",
		"zlfbrq": 1430984415000,
		"zlcxyy": null,
		"zlnzoa": null,
		"zloaid": null,
		"zldq": "00000000",
		"zldqmc": "中华人民共和国",
		"zlfwzg": null,
		"zlsfdl": "0",
		"zlsfzcyh": "0",
		"zldxlx": "00000000000000000000003",
		"zldqbbh": "0000000002015050700007002",
		"zldffg": null,
		"zlxf": null,
		"zlywczr": null,
		"zltypemc": "税收法规->其他地方规费",
		"zlhytypemc": "通用政策",
		"zlfz": 15,
		"zlisdel": "0",
		"zlwzfgbh": null,
		"zldxlxmc": "全部",
		"zlcxlcid": null,
		"gxsj": "2015-05-07 15:40:15",
		"bbh": null,
		"jhzt": "1",
		"xzqh": "000000000",
		"zlcxsqr": null,
		"zldlssid": "0",
		"zldlxh": null,
		"zlsxczbs": "0",
		"zlsfjs": "0",
		"zlsfzjsh": "0",
		"zlzgdw": null,
		"zlzgdwmc": null
	}, {
		"zlcode": "0000000002015050400010",
		"zlwfid": null,
		"activityid": null,
		"zljm": "38127",
		"zltitle": "财政部 国家发展改革委关于清理涉及稀土、钨、钼收费基金有关问题的通知",
		"zlgjz": "矿产资源补偿费 价格调节基金 稀土 钨 钼 资源税",
		"zlflag": "1",
		"zltype": "“1“000000000122“",
		"zlhytype": "00000000000000000000040",
		"zllywj": "0000000002015050400010.voc",
		"zlczwj": null,
		"zllrr": "ssfgcj001",
		"zllrsj": "2015-05-04",
		"zllrdw": "第七运维中心",
		"zlzt": "60",
		"zlsfyx": "0",
		"zlsffb": "1",
		"zlfbr": "system",
		"zlly": null,
		"zlsz": "0",
		"zlwh": "财税〔2015〕53号",
		"zlfwdw": "财政部 国家发展改革委",
		"zlbfrq": 1430380080000,
		"zlsxrq": null,
		"zlssrq": 1430466480000,
		"zlwjdj": "3",
		"zlsydj": "0",
		"zlnowshr": null,
		"zlnowshjs": null,
		"zlnowjg": null,
		"zlnowbm": null,
		"zlzhczr": "ssfgsh001",
		"zlzhczsj": 1430725918000,
		"lastczr": null,
		"zlqzz": null,
		"zlwxyy": null,
		"zlzy": null,
		"zlpz": null,
		"zlsfgk": "0",
		"zlfbrq": 1430725918000,
		"zlcxyy": null,
		"zlnzoa": null,
		"zloaid": null,
		"zldq": "00000000",
		"zldqmc": "中华人民共和国",
		"zlfwzg": null,
		"zlsfdl": "0",
		"zlsfzcyh": "0",
		"zldxlx": "00000000000000000000003",
		"zldqbbh": "0000000002015050400010002",
		"zldffg": null,
		"zlxf": null,
		"zlywczr": null,
		"zltypemc": "税收法规->其他地方规费",
		"zlhytypemc": "通用政策",
		"zlfz": 5,
		"zlisdel": "0",
		"zlwzfgbh": null,
		"zldxlxmc": "全部",
		"zlcxlcid": null,
		"gxsj": "2015-05-04 15:51:58",
		"bbh": null,
		"jhzt": "1",
		"xzqh": "000000000",
		"zlcxsqr": null,
		"zldlssid": "0",
		"zldlxh": null,
		"zlsxczbs": "0",
		"zlsfjs": "0",
		"zlsfzjsh": "0",
		"zlzgdw": null,
		"zlzgdwmc": null
	}, {
		"zlcode": "0000000002015030400007",
		"zlwfid": null,
		"activityid": null,
		"zljm": "37829",
		"zltitle": "国家税务总局 财政部 人力资源社会保障部教育部 民政部关于支持和促进重点群体创业就业有关税收政策具体实施问题的补充公告",
		"zlgjz": "营业税 城市维护建设税 教育费附加 个人所得税 重点群体 创业就业",
		"zlflag": "1",
		"zltype": "“4“000000000401“00000000040111“0000000004011101“,“1“000000000105“,“1“000000000107“,“1“000000000109“,“1“000000000122“00000000012201“",
		"zlhytype": "00000000000000000000040",
		"zllywj": "0000000002015030400007.voc",
		"zlczwj": null,
		"zllrr": "ssfgcj001",
		"zllrsj": "2015-03-04",
		"zllrdw": "第七运维中心",
		"zlzt": "60",
		"zlsfyx": "0",
		"zlsffb": "1",
		"zlfbr": "system",
		"zlly": null,
		"zlsz": "0",
		"zlwh": "国家税务总局 财政部 人力资源社会保障部 教育部 民政部公告2015年第12号",
		"zlfwdw": "国家税务总局 财政部 人力资源社会保障部 教育部 民政部",
		"zlbfrq": 1423808996000,
		"zlsxrq": null,
		"zlssrq": 1423808996000,
		"zlwjdj": "3",
		"zlsydj": "0",
		"zlnowshr": null,
		"zlnowshjs": null,
		"zlnowjg": null,
		"zlnowbm": null,
		"zlzhczr": "ssfgsh001",
		"zlzhczsj": 1425450932000,
		"lastczr": null,
		"zlqzz": null,
		"zlwxyy": null,
		"zlzy": null,
		"zlpz": null,
		"zlsfgk": "0",
		"zlfbrq": 1425450932000,
		"zlcxyy": null,
		"zlnzoa": null,
		"zloaid": null,
		"zldq": "00000000",
		"zldqmc": "中华人民共和国",
		"zlfwzg": null,
		"zlsfdl": "0",
		"zlsfzcyh": "0",
		"zldxlx": "00000000000000000000003",
		"zldqbbh": "0000000002015030400007002",
		"zldffg": null,
		"zlxf": null,
		"zlywczr": null,
		"zltypemc": "税收法规->营业税；税收法规->个人所得税；税收法规->城市维护建设税；税收法规->其他地方规费->教育费附加；业务专题->税收优惠政策->促进就业税收政策->下岗再就业税收政策",
		"zlhytypemc": "通用政策",
		"zlfz": 28,
		"zlisdel": "0",
		"zlwzfgbh": null,
		"zldxlxmc": "全部",
		"zlcxlcid": null,
		"gxsj": "2015-03-04 14:35:32",
		"bbh": null,
		"jhzt": "1",
		"xzqh": "000000000",
		"zlcxsqr": null,
		"zldlssid": "0",
		"zldlxh": null,
		"zlsxczbs": "0",
		"zlsfjs": "0",
		"zlsfzjsh": "0",
		"zlzgdw": null,
		"zlzgdwmc": null
	}, {
		"zlcode": "0000000002015022500010",
		"zlwfid": null,
		"activityid": null,
		"zljm": "37806",
		"zltitle": "财政部 海关总署 国家税务总局关于支持鲁甸地震灾后恢复重建有关税收政策问题的通知",
		"zlgjz": "鲁甸 企业所得税 进出口税收 土地增值税 耕地占用税 印花税 契税 房产税 城镇土地使用税 城市维护建设税 增值税 其他地方规费 车辆购置税 营业税",
		"zlflag": "1",
		"zltype": "“1“000000000105“,“1“000000000115“,“1“000000000122“,“1“000000000103“,“1“000000000109“,“1“000000000112“,“1“000000000110“,“1“000000000118“,“1“000000000111“,“1“000000000117“,“1“000000000113“,“1“000000000119“,“1“000000000106“",
		"zlhytype": "00000000000000000000040",
		"zllywj": "0000000002015022500010.voc",
		"zlczwj": null,
		"zllrr": "ssfgcj001",
		"zllrsj": "2015-02-25",
		"zllrdw": "第七运维中心",
		"zlzt": "60",
		"zlsfyx": "0",
		"zlsffb": "1",
		"zlfbr": "system",
		"zlly": null,
		"zlsz": "0",
		"zlwh": "财税〔2015〕27号",
		"zlfwdw": "财政部 海关总署 国家税务总局",
		"zlbfrq": 1422258685000,
		"zlsxrq": null,
		"zlssrq": 1388562685000,
		"zlwjdj": "3",
		"zlsydj": "0",
		"zlnowshr": null,
		"zlnowshjs": null,
		"zlnowjg": null,
		"zlnowbm": null,
		"zlzhczr": "ssfgsh001",
		"zlzhczsj": 1425004705000,
		"lastczr": null,
		"zlqzz": null,
		"zlwxyy": null,
		"zlzy": null,
		"zlpz": null,
		"zlsfgk": "0",
		"zlfbrq": 1425004705000,
		"zlcxyy": null,
		"zlnzoa": null,
		"zloaid": null,
		"zldq": "00000000",
		"zldqmc": "中华人民共和国",
		"zlfwzg": null,
		"zlsfdl": "0",
		"zlsfzcyh": "0",
		"zldxlx": "00000000000000000000003",
		"zldqbbh": "0000000002015022500010002",
		"zldffg": null,
		"zlxf": null,
		"zlywczr": null,
		"zltypemc": "税收法规->企业所得税；税收法规->进出口税收；税收法规->土地增值税；税收法规->耕地占用税；税收法规->印花税；税收法规->契税；税收法规->房产税；税收法规->城镇土地使用税；税收法规->城市维护建设税；税收法规->增值税；税收法规->其他地方规费；税收法规->车辆购置税；税收法规->营业税",
		"zlhytypemc": "通用政策",
		"zlfz": 24,
		"zlisdel": "0",
		"zlwzfgbh": null,
		"zldxlxmc": "全部",
		"zlcxlcid": null,
		"gxsj": "2015-02-27 10:38:25",
		"bbh": null,
		"jhzt": "1",
		"xzqh": "000000000",
		"zlcxsqr": null,
		"zldlssid": "0",
		"zldlxh": null,
		"zlsxczbs": "0",
		"zlsfjs": "0",
		"zlsfzjsh": "0",
		"zlzgdw": null,
		"zlzgdwmc": null
	}, {
		"zlcode": "0000000002014122600004",
		"zlwfid": null,
		"activityid": null,
		"zljm": "37565",
		"zltitle": "财政部 国家税务总局关于对小微企业免征有关政府性基金的通知",
		"zlgjz": "教育费附加 文化事业建设费 残疾人就业保障金 地方教育附加 水利建设基金",
		"zlflag": "1",
		"zltype": "“4“000000000401“00000000040105“,“1“000000000122“",
		"zlhytype": "00000000000000000000040",
		"zllywj": "0000000002014122600004.voc",
		"zlczwj": null,
		"zllrr": "ssfgcj001",
		"zllrsj": "2015-02-10",
		"zllrdw": "第七运维中心",
		"zlzt": "60",
		"zlsfyx": "0",
		"zlsffb": "1",
		"zlfbr": "system",
		"zlly": null,
		"zlsz": "0",
		"zlwh": "财税〔2014〕122号",
		"zlfwdw": "财政部 国家税务总局",
		"zlbfrq": 1419321225000,
		"zlsxrq": null,
		"zlssrq": null,
		"zlwjdj": "3",
		"zlsydj": "0",
		"zlnowshr": null,
		"zlnowshjs": null,
		"zlnowjg": null,
		"zlnowbm": null,
		"zlzhczr": "ssfgsh001",
		"zlzhczsj": 1423554965000,
		"lastczr": null,
		"zlqzz": null,
		"zlwxyy": null,
		"zlzy": null,
		"zlpz": null,
		"zlsfgk": "0",
		"zlfbrq": 1423554965000,
		"zlcxyy": null,
		"zlnzoa": null,
		"zloaid": null,
		"zldq": "00000000",
		"zldqmc": "中华人民共和国",
		"zlfwzg": null,
		"zlsfdl": "0",
		"zlsfzcyh": "0",
		"zldxlx": "00000000000000000000003",
		"zldqbbh": "0000000002014122600004004",
		"zldffg": null,
		"zlxf": null,
		"zlywczr": null,
		"zltypemc": "税收法规->其他地方规费；业务专题->税收优惠政策->中小企业税收政策",
		"zlhytypemc": "通用政策",
		"zlfz": 1310,
		"zlisdel": "0",
		"zlwzfgbh": null,
		"zldxlxmc": "全部",
		"zlcxlcid": null,
		"gxsj": "2015-02-10 15:56:05",
		"bbh": null,
		"jhzt": "1",
		"xzqh": "000000000",
		"zlcxsqr": null,
		"zldlssid": "0",
		"zldlxh": null,
		"zlsxczbs": "0",
		"zlsfjs": "0",
		"zlsfzjsh": "0",
		"zlzgdw": null,
		"zlzgdwmc": null
	}, {
		"zlcode": "0000000002015021000005",
		"zlwfid": null,
		"activityid": null,
		"zljm": "37782",
		"zltitle": "财政部 国家发展改革委关于重新发布中国银行业监督管理委员行政事业性收费项目的通知",
		"zlgjz": "行政事业性收费 银行业 银行业监管费",
		"zlflag": "1",
		"zltype": "“1“000000000122“",
		"zlhytype": "00000000000000000000040",
		"zllywj": "0000000002015021000005.voc",
		"zlczwj": null,
		"zllrr": "ssfgcj001",
		"zllrsj": "2015-02-10",
		"zllrdw": "第七运维中心",
		"zlzt": "60",
		"zlsfyx": "0",
		"zlsffb": "1",
		"zlfbr": "system",
		"zlly": null,
		"zlsz": "0",
		"zlwh": "财税〔2015〕21号",
		"zlfwdw": "财政部 国家发展改革委",
		"zlbfrq": 1422328272000,
		"zlsxrq": null,
		"zlssrq": 1422328272000,
		"zlwjdj": "3",
		"zlsydj": "0",
		"zlnowshr": null,
		"zlnowshjs": null,
		"zlnowjg": null,
		"zlnowbm": null,
		"zlzhczr": "ssfgsh001",
		"zlzhczsj": 1423538139000,
		"lastczr": null,
		"zlqzz": null,
		"zlwxyy": null,
		"zlzy": null,
		"zlpz": null,
		"zlsfgk": "0",
		"zlfbrq": 1423538139000,
		"zlcxyy": null,
		"zlnzoa": null,
		"zloaid": null,
		"zldq": "00000000",
		"zldqmc": "中华人民共和国",
		"zlfwzg": null,
		"zlsfdl": "0",
		"zlsfzcyh": "0",
		"zldxlx": "00000000000000000000003",
		"zldqbbh": "0000000002015021000005002",
		"zldffg": null,
		"zlxf": null,
		"zlywczr": null,
		"zltypemc": "税收法规->其他地方规费",
		"zlhytypemc": "通用政策",
		"zlfz": 8,
		"zlisdel": "0",
		"zlwzfgbh": null,
		"zldxlxmc": "全部",
		"zlcxlcid": null,
		"gxsj": "2015-02-10 11:15:39",
		"bbh": null,
		"jhzt": "1",
		"xzqh": "000000000",
		"zlcxsqr": null,
		"zldlssid": "0",
		"zldlxh": null,
		"zlsxczbs": "0",
		"zlsfjs": "0",
		"zlsfzjsh": "0",
		"zlzgdw": null,
		"zlzgdwmc": null
	}, {
		"zlcode": "0000000002015021000003",
		"zlwfid": null,
		"activityid": null,
		"zljm": "37780",
		"zltitle": "财政部 国家发展改革委关于重新发布中国证券监督管理委员会行政事业性收费项目的通知",
		"zlgjz": "行政事业性收费 金融 证券、期货业监管费 证券、期货、基金从业人员资格考试费",
		"zlflag": "1",
		"zltype": "“1“000000000122“",
		"zlhytype": "00000000000000000000040",
		"zllywj": "0000000002015021000003.voc",
		"zlczwj": null,
		"zllrr": "ssfgcj001",
		"zllrsj": "2015-02-10",
		"zllrdw": "第七运维中心",
		"zlzt": "60",
		"zlsfyx": "0",
		"zlsffb": "1",
		"zlfbr": "system",
		"zlly": null,
		"zlsz": "0",
		"zlwh": "财税〔2015〕20号",
		"zlfwdw": "财政部 国家发展改革委",
		"zlbfrq": 1422326928000,
		"zlsxrq": null,
		"zlssrq": 1422326928000,
		"zlwjdj": "3",
		"zlsydj": "0",
		"zlnowshr": null,
		"zlnowshjs": null,
		"zlnowjg": null,
		"zlnowbm": null,
		"zlzhczr": "ssfgsh001",
		"zlzhczsj": 1423536790000,
		"lastczr": null,
		"zlqzz": null,
		"zlwxyy": null,
		"zlzy": null,
		"zlpz": null,
		"zlsfgk": "0",
		"zlfbrq": 1423536790000,
		"zlcxyy": null,
		"zlnzoa": null,
		"zloaid": null,
		"zldq": "00000000",
		"zldqmc": "中华人民共和国",
		"zlfwzg": null,
		"zlsfdl": "0",
		"zlsfzcyh": "0",
		"zldxlx": "00000000000000000000003",
		"zldqbbh": "0000000002015021000003002",
		"zldffg": null,
		"zlxf": null,
		"zlywczr": null,
		"zltypemc": "税收法规->其他地方规费",
		"zlhytypemc": "通用政策",
		"zlfz": 9,
		"zlisdel": "0",
		"zlwzfgbh": null,
		"zldxlxmc": "全部",
		"zlcxlcid": null,
		"gxsj": "2015-02-10 10:53:10",
		"bbh": null,
		"jhzt": "1",
		"xzqh": "000000000",
		"zlcxsqr": null,
		"zldlssid": "0",
		"zldlxh": null,
		"zlsxczbs": "0",
		"zlsfjs": "0",
		"zlsfzjsh": "0",
		"zlzgdw": null,
		"zlzgdwmc": null
	}, {
		"zlcode": "0000000002015021000001",
		"zlwfid": null,
		"activityid": null,
		"zljm": "37778",
		"zltitle": "财政部 国家发展改革委关于重新发布中国保险监督管理委员会行政事业性收费项目的通知",
		"zlgjz": "行政事业性收费 保险业监管费 保险代理人资格考试费和保险经纪人资格考试费",
		"zlflag": "1",
		"zltype": "“1“000000000122“",
		"zlhytype": "00000000000000000000040",
		"zllywj": "0000000002015021000001.voc",
		"zlczwj": null,
		"zllrr": "ssfgcj001",
		"zllrsj": "2015-02-10",
		"zllrdw": "第七运维中心",
		"zlzt": "60",
		"zlsfyx": "0",
		"zlsffb": "1",
		"zlfbr": "system",
		"zlly": null,
		"zlsz": "0",
		"zlwh": "财税〔2015〕22号",
		"zlfwdw": "财政部 国家发展改革委",
		"zlbfrq": 1422323440000,
		"zlsxrq": null,
		"zlssrq": 1422323440000,
		"zlwjdj": "3",
		"zlsydj": "0",
		"zlnowshr": null,
		"zlnowshjs": null,
		"zlnowjg": null,
		"zlnowbm": null,
		"zlzhczr": "ssfgsh001",
		"zlzhczsj": 1423533301000,
		"lastczr": null,
		"zlqzz": null,
		"zlwxyy": null,
		"zlzy": null,
		"zlpz": null,
		"zlsfgk": "0",
		"zlfbrq": 1423533301000,
		"zlcxyy": null,
		"zlnzoa": null,
		"zloaid": null,
		"zldq": "00000000",
		"zldqmc": "中华人民共和国",
		"zlfwzg": null,
		"zlsfdl": "0",
		"zlsfzcyh": "0",
		"zldxlx": "00000000000000000000003",
		"zldqbbh": "0000000002015021000001002",
		"zldffg": null,
		"zlxf": null,
		"zlywczr": null,
		"zltypemc": "税收法规->其他地方规费",
		"zlhytypemc": "通用政策",
		"zlfz": 7,
		"zlisdel": "0",
		"zlwzfgbh": null,
		"zldxlxmc": "全部",
		"zlcxlcid": null,
		"gxsj": "2015-02-10 09:55:01",
		"bbh": null,
		"jhzt": "1",
		"xzqh": "000000000",
		"zlcxsqr": null,
		"zldlssid": "0",
		"zldlxh": null,
		"zlsxczbs": "0",
		"zlsfjs": "0",
		"zlsfzjsh": "0",
		"zlzgdw": null,
		"zlzgdwmc": null
	}],
	"totalItems": 186,
	"totalPages": 7,
	"nextPage": 2,
	"prePage": 1,
	"sort": [{
		"property": "zllrsj",
		"dir": "desc"
	}],
	"orderBySetted": true,
	"offset": 0,
	"orderSortString": "zllrsj desc"
}