{
	"pageNo": 1,
	"pageSize": 30,
	"orderBy": "zllrsj",
	"orderDir": "desc",
	"countTotal": true,
	"result": [{
		"zlcode": "0000000002010102726702",
		"zlwfid": null,
		"activityid": null,
		"zljm": "28946",
		"zltitle": "财政部关于印发《行政事业单位资金往来结算票据使用管理暂行办法》的通知",
		"zlgjz": "行政事业单位 资金往来 票据使用 管理 暂行办法",
		"zlflag": "1",
		"zltype": "“1“000000000123“",
		"zlhytype": "00000000000000000000040",
		"zllywj": "0000000002010102726702.voc",
		"zlczwj": null,
		"zllrr": "总局超管",
		"zllrsj": "2015-11-23",
		"zllrdw": null,
		"zlzt": "60",
		"zlsfyx": "0",
		"zlsffb": "1",
		"zlfbr": "system",
		"zlly": null,
		"zlsz": "0",
		"zlwh": "财综〔2010〕1号",
		"zlfwdw": "财政部",
		"zlbfrq": 1262676368000,
		"zlsxrq": null,
		"zlssrq": 1277969168000,
		"zlwjdj": "3",
		"zlsydj": "0",
		"zlnowshr": null,
		"zlnowshjs": null,
		"zlnowjg": null,
		"zlnowbm": null,
		"zlzhczr": "zssh001",
		"zlzhczsj": 1448265130000,
		"lastczr": null,
		"zlqzz": null,
		"zlwxyy": null,
		"zlzy": null,
		"zlpz": "F-1-79",
		"zlsfgk": "0",
		"zlfbrq": 1448265130000,
		"zlcxyy": null,
		"zlnzoa": null,
		"zloaid": null,
		"zldq": "00000000",
		"zldqmc": "中华人民共和国",
		"zlfwzg": null,
		"zlsfdl": "0",
		"zlsfzcyh": "0",
		"zldxlx": "00000000000000000000003",
		"zldqbbh": "00000000000000000145897002",
		"zldffg": null,
		"zlxf": null,
		"zlywczr": null,
		"zltypemc": "税收法规->财务会计",
		"zlhytypemc": "通用政策",
		"zlfz": 52,
		"zlisdel": "0",
		"zlwzfgbh": null,
		"zldxlxmc": "全部",
		"zlcxlcid": null,
		"gxsj": "2015-11-23 15:52:10",
		"bbh": null,
		"jhzt": "1",
		"xzqh": "000000000",
		"zlcxsqr": null,
		"zldlssid": "0",
		"zldlxh": null,
		"zlsxczbs": null,
		"zlsfjs": "0",
		"zlsfzjsh": "0",
		"zlzgdw": null,
		"zlzgdwmc": null
	}, {
		"zlcode": "0000000002014120300021",
		"zlwfid": null,
		"activityid": null,
		"zljm": "37404",
		"zltitle": "财政部关于印发《小企业会计准则》的通知",
		"zlgjz": "小企业会计准则",
		"zlflag": "1",
		"zltype": "“1“000000000123“",
		"zlhytype": "00000000000000000000040",
		"zllywj": "0000000002014120300021.voc",
		"zlczwj": null,
		"zllrr": "ssfgcj001",
		"zllrsj": "2014-12-03",
		"zllrdw": "第七运维中心",
		"zlzt": "60",
		"zlsfyx": "0",
		"zlsffb": "1",
		"zlfbr": "system",
		"zlly": null,
		"zlsz": "0",
		"zlwh": "财会〔2011〕17号",
		"zlfwdw": "财政部",
		"zlbfrq": 1318926392000,
		"zlsxrq": null,
		"zlssrq": 1357028792000,
		"zlwjdj": "3",
		"zlsydj": "0",
		"zlnowshr": null,
		"zlnowshjs": null,
		"zlnowjg": null,
		"zlnowbm": null,
		"zlzhczr": "ssfgsh001",
		"zlzhczsj": 1417595892000,
		"lastczr": null,
		"zlqzz": null,
		"zlwxyy": null,
		"zlzy": null,
		"zlpz": null,
		"zlsfgk": "0",
		"zlfbrq": 1417595892000,
		"zlcxyy": null,
		"zlnzoa": null,
		"zloaid": null,
		"zldq": "00000000",
		"zldqmc": "中华人民共和国",
		"zlfwzg": null,
		"zlsfdl": "0",
		"zlsfzcyh": "0",
		"zldxlx": "00000000000000000000003",
		"zldqbbh": "0000000002014120300021002",
		"zldffg": null,
		"zlxf": null,
		"zlywczr": null,
		"zltypemc": "税收法规->财务会计",
		"zlhytypemc": "通用政策",
		"zlfz": 86,
		"zlisdel": "0",
		"zlwzfgbh": null,
		"zldxlxmc": "全部",
		"zlcxlcid": null,
		"gxsj": "2014-12-03 16:38:12",
		"bbh": null,
		"jhzt": "1",
		"xzqh": "000000000",
		"zlcxsqr": null,
		"zldlssid": "0",
		"zldlxh": null,
		"zlsxczbs": "0",
		"zlsfjs": "0",
		"zlsfzjsh": "0",
		"zlzgdw": null,
		"zlzgdwmc": null
	}, {
		"zlcode": "0000000002010102723477",
		"zlwfid": null,
		"activityid": null,
		"zljm": "25721",
		"zltitle": "小企业会计制度",
		"zlgjz": "小企业 会计制度",
		"zlflag": "1",
		"zltype": "“1“000000000123“",
		"zlhytype": "00000000000000000000040",
		"zllywj": "0000000002010102723477.voc",
		"zlczwj": null,
		"zllrr": "总局超管",
		"zllrsj": "2014-12-03",
		"zllrdw": null,
		"zlzt": "60",
		"zlsfyx": "1",
		"zlsffb": "1",
		"zlfbr": "system",
		"zlly": null,
		"zlsz": "0",
		"zlwh": "财会〔2004〕2号",
		"zlfwdw": "财政部",
		"zlbfrq": 1083053792000,
		"zlsxrq": 1357028192000,
		"zlssrq": null,
		"zlwjdj": "3",
		"zlsydj": "0",
		"zlnowshr": null,
		"zlnowshjs": null,
		"zlnowjg": null,
		"zlnowbm": null,
		"zlzhczr": "ssfgsh001",
		"zlzhczsj": 1417595294000,
		"lastczr": null,
		"zlqzz": null,
		"zlwxyy": "根据《财政部关于印发<小企业会计准则>的通知》（财会〔2011〕17号）的规定：“我部制定了《小企业会计准则》，现予印发，自2013年1月1日起在小企业范围内施行，鼓励小企业提前执行。我部于2004年4月27日发布的《小企业会计制度》（财会〔2004〕2号）同时废止。”",
		"zlzy": null,
		"zlpz": "F-1-54",
		"zlsfgk": "0",
		"zlfbrq": 1417595294000,
		"zlcxyy": null,
		"zlnzoa": null,
		"zloaid": null,
		"zldq": "00000000",
		"zldqmc": "中华人民共和国",
		"zlfwzg": null,
		"zlsfdl": "0",
		"zlsfzcyh": "0",
		"zldxlx": "00000000000000000000003",
		"zldqbbh": "00000000000000000142672002",
		"zldffg": null,
		"zlxf": null,
		"zlywczr": null,
		"zltypemc": "税收法规->财务会计",
		"zlhytypemc": "通用政策",
		"zlfz": 50,
		"zlisdel": "0",
		"zlwzfgbh": null,
		"zldxlxmc": "全部",
		"zlcxlcid": null,
		"gxsj": "2014-12-03 16:28:14",
		"bbh": null,
		"jhzt": "1",
		"xzqh": "000000000",
		"zlcxsqr": null,
		"zldlssid": "0",
		"zldlxh": null,
		"zlsxczbs": null,
		"zlsfjs": "0",
		"zlsfzjsh": "1",
		"zlzgdw": null,
		"zlzgdwmc": null
	}, {
		"zlcode": "0000000002013010600004",
		"zlwfid": null,
		"activityid": null,
		"zljm": "34384",
		"zltitle": "财政部关于印发《小企业执行〈小企业会计准则〉有关问题衔接规定》的通知",
		"zlgjz": "小企业 会计准则",
		"zlflag": "1",
		"zltype": "“1“000000000123“",
		"zlhytype": "00000000000000000000040",
		"zllywj": "0000000002013010600004.voc",
		"zlczwj": null,
		"zllrr": "ssfgcj001",
		"zllrsj": "2014-07-10",
		"zllrdw": "第七运维中心",
		"zlzt": "60",
		"zlsfyx": "0",
		"zlsffb": "1",
		"zlfbr": "system",
		"zlly": null,
		"zlsz": "0",
		"zlwh": "财会〔2012〕20号",
		"zlfwdw": "财政部",
		"zlbfrq": 1351500799000,
		"zlsxrq": null,
		"zlssrq": null,
		"zlwjdj": "3",
		"zlsydj": "0",
		"zlnowshr": null,
		"zlnowshjs": null,
		"zlnowjg": null,
		"zlnowbm": null,
		"zlzhczr": "ssfgsh001",
		"zlzhczsj": 1404985651000,
		"lastczr": null,
		"zlqzz": null,
		"zlwxyy": null,
		"zlzy": null,
		"zlpz": null,
		"zlsfgk": "0",
		"zlfbrq": 1404985651000,
		"zlcxyy": null,
		"zlnzoa": null,
		"zloaid": null,
		"zldq": "00000000",
		"zldqmc": "中华人民共和国",
		"zlfwzg": null,
		"zlsfdl": "0",
		"zlsfzcyh": "0",
		"zldxlx": "00000000000000000000003",
		"zldqbbh": "0000000002013010600004003",
		"zldffg": null,
		"zlxf": null,
		"zlywczr": null,
		"zltypemc": "税收法规->财务会计",
		"zlhytypemc": "通用政策",
		"zlfz": 26,
		"zlisdel": "0",
		"zlwzfgbh": null,
		"zldxlxmc": "全部",
		"zlcxlcid": null,
		"gxsj": "2014-07-10 17:47:31",
		"bbh": null,
		"jhzt": "1",
		"xzqh": "000000000",
		"zlcxsqr": null,
		"zldlssid": "0",
		"zldlxh": null,
		"zlsxczbs": "0",
		"zlsfjs": "0",
		"zlsfzjsh": "1",
		"zlzgdw": null,
		"zlzgdwmc": null
	}, {
		"zlcode": "0000000002012110800003",
		"zlwfid": null,
		"activityid": "11370857_9730173_pkg_zsk_zskshlc_wp1_toShiCS",
		"zljm": "34266",
		"zltitle": "关于印发《小企业会计准则》的通知",
		"zlgjz": null,
		"zlflag": "1",
		"zltype": "“1“000000000123“00000000012301“",
		"zlhytype": "00000000000000000000040",
		"zllywj": "0000000002012110800003.voc",
		"zlczwj": null,
		"zllrr": "cwkjcj1",
		"zllrsj": "2014-07-10",
		"zllrdw": "五中心财务会计组",
		"zlzt": "60",
		"zlsfyx": "0",
		"zlsffb": "1",
		"zlfbr": "system",
		"zlly": null,
		"zlsz": "0",
		"zlwh": "财会[2011]17号",
		"zlfwdw": "财政部",
		"zlbfrq": 1318062414000,
		"zlsxrq": null,
		"zlssrq": 1357028814000,
		"zlwjdj": "3",
		"zlsydj": "0",
		"zlnowshr": null,
		"zlnowshjs": null,
		"zlnowjg": null,
		"zlnowbm": null,
		"zlzhczr": "总局超管",
		"zlzhczsj": 1404983905000,
		"lastczr": null,
		"zlqzz": null,
		"zlwxyy": null,
		"zlzy": null,
		"zlpz": null,
		"zlsfgk": "0",
		"zlfbrq": 1404983905000,
		"zlcxyy": null,
		"zlnzoa": null,
		"zloaid": null,
		"zldq": "00000000",
		"zldqmc": "中华人民共和国",
		"zlfwzg": null,
		"zlsfdl": "0",
		"zlsfzcyh": "0",
		"zldxlx": "00000000000000000000003",
		"zldqbbh": "0000000002012110800003003",
		"zldffg": null,
		"zlxf": null,
		"zlywczr": null,
		"zltypemc": "税收法规->财务会计->会计法规制度",
		"zlhytypemc": "通用政策",
		"zlfz": 225,
		"zlisdel": "0",
		"zlwzfgbh": null,
		"zldxlxmc": "全部",
		"zlcxlcid": null,
		"gxsj": "2014-07-10 17:18:25",
		"bbh": null,
		"jhzt": "1",
		"xzqh": "000000000",
		"zlcxsqr": null,
		"zldlssid": "0",
		"zldlxh": null,
		"zlsxczbs": "0",
		"zlsfjs": "0",
		"zlsfzjsh": "1",
		"zlzgdw": null,
		"zlzgdwmc": null
	}, {
		"zlcode": "0000000002012123100007",
		"zlwfid": null,
		"activityid": "11371352_9730259_pkg_zsk_zskshlc_wp1_toShengCS",
		"zljm": "34373",
		"zltitle": "国家税务总局 中国人民银行 财政部关于跨省合资铁路企业跨地区税收分享入库有关问题的通知",
		"zlgjz": "铁路企业 跨地区 营业税 企业所得税 税款",
		"zlflag": "1",
		"zltype": "“1“000000000123“",
		"zlhytype": "00000000000000000000040",
		"zllywj": "0000000002012123100007.voc",
		"zlczwj": null,
		"zllrr": "ssfgcj001",
		"zllrsj": "2014-07-10",
		"zllrdw": "第七运维中心",
		"zlzt": "60",
		"zlsfyx": "0",
		"zlsffb": "1",
		"zlfbr": "system",
		"zlly": null,
		"zlsz": "0",
		"zlwh": "国税发〔2012〕116号",
		"zlfwdw": "国家税务总局 中国人民银行 财政部",
		"zlbfrq": 1355386844000,
		"zlsxrq": null,
		"zlssrq": 1357028444000,
		"zlwjdj": "3",
		"zlsydj": "0",
		"zlnowshr": null,
		"zlnowshjs": null,
		"zlnowjg": null,
		"zlnowbm": null,
		"zlzhczr": "ssfgsh001",
		"zlzhczsj": 1404985659000,
		"lastczr": null,
		"zlqzz": null,
		"zlwxyy": null,
		"zlzy": null,
		"zlpz": null,
		"zlsfgk": "0",
		"zlfbrq": 1404985659000,
		"zlcxyy": null,
		"zlnzoa": null,
		"zloaid": null,
		"zldq": "00000000",
		"zldqmc": "中华人民共和国",
		"zlfwzg": null,
		"zlsfdl": "0",
		"zlsfzcyh": "0",
		"zldxlx": "00000000000000000000003",
		"zldqbbh": "0000000002012123100007003",
		"zldffg": null,
		"zlxf": null,
		"zlywczr": null,
		"zltypemc": "税收法规->财务会计",
		"zlhytypemc": "通用政策",
		"zlfz": 38,
		"zlisdel": "0",
		"zlwzfgbh": null,
		"zldxlxmc": "全部",
		"zlcxlcid": null,
		"gxsj": "2014-07-10 17:47:39",
		"bbh": null,
		"jhzt": "1",
		"xzqh": "000000000",
		"zlcxsqr": null,
		"zldlssid": "0",
		"zldlxh": null,
		"zlsxczbs": "0",
		"zlsfjs": "0",
		"zlsfzjsh": "1",
		"zlzgdw": null,
		"zlzgdwmc": null
	}, {
		"zlcode": "0000000002010102723461",
		"zlwfid": null,
		"activityid": null,
		"zljm": "25705",
		"zltitle": "财政部关于印发《基本建设财务管理若干规定》的通知",
		"zlgjz": "基本建设 财务管理 ",
		"zlflag": "1",
		"zltype": "“1“000000000123“",
		"zlhytype": "00000000000000000000040",
		"zllywj": "0000000002010102723461.voc",
		"zlczwj": null,
		"zllrr": "总局超管",
		"zllrsj": "2012-10-25",
		"zllrdw": null,
		"zlzt": "60",
		"zlsfyx": "0",
		"zlsffb": "1",
		"zlfbr": "system",
		"zlly": null,
		"zlsz": "0",
		"zlwh": "财基字〔1998〕4号",
		"zlfwdw": "财政部",
		"zlbfrq": 888216571000,
		"zlsxrq": null,
		"zlssrq": 883637371000,
		"zlwjdj": "3",
		"zlsydj": "0",
		"zlnowshr": null,
		"zlnowshjs": null,
		"zlnowjg": null,
		"zlnowbm": null,
		"zlzhczr": "zjsh",
		"zlzhczsj": 1351150601000,
		"lastczr": null,
		"zlqzz": null,
		"zlwxyy": null,
		"zlzy": null,
		"zlpz": "F-1-32",
		"zlsfgk": "0",
		"zlfbrq": 1351150601000,
		"zlcxyy": null,
		"zlnzoa": null,
		"zloaid": null,
		"zldq": "00000000",
		"zldqmc": "中华人民共和国",
		"zlfwzg": null,
		"zlsfdl": "0",
		"zlsfzcyh": "0",
		"zldxlx": "00000000000000000000003",
		"zldqbbh": "00000000000000000142656001",
		"zldffg": null,
		"zlxf": null,
		"zlywczr": null,
		"zltypemc": "税收法规->财务会计",
		"zlhytypemc": "通用政策",
		"zlfz": 52,
		"zlisdel": "0",
		"zlwzfgbh": null,
		"zldxlxmc": "全部",
		"zlcxlcid": null,
		"gxsj": null,
		"bbh": null,
		"jhzt": "1",
		"xzqh": "000000000",
		"zlcxsqr": null,
		"zldlssid": "0",
		"zldlxh": null,
		"zlsxczbs": null,
		"zlsfjs": "0",
		"zlsfzjsh": "1",
		"zlzgdw": null,
		"zlzgdwmc": null
	}, {
		"zlcode": "0000000002010102723456",
		"zlwfid": null,
		"activityid": null,
		"zljm": "25700",
		"zltitle": "国家税务总局关于转发财政部《事业单位财务规则》的通知",
		"zlgjz": "事业单位 财务规则",
		"zlflag": "1",
		"zltype": "“1“000000000123“",
		"zlhytype": "00000000000000000000040",
		"zllywj": "0000000002010102723456.voc",
		"zlczwj": null,
		"zllrr": "总局超管",
		"zllrsj": "2012-10-25",
		"zllrdw": null,
		"zlzt": "60",
		"zlsfyx": "0",
		"zlsffb": "1",
		"zlfbr": "system",
		"zlly": null,
		"zlsz": "0",
		"zlwh": "国税发〔1996〕237号",
		"zlfwdw": "国家税务总局",
		"zlbfrq": 851582929000,
		"zlsxrq": null,
		"zlssrq": 852101329000,
		"zlwjdj": "3",
		"zlsydj": "0",
		"zlnowshr": null,
		"zlnowshjs": null,
		"zlnowjg": null,
		"zlnowbm": null,
		"zlzhczr": "zjsh",
		"zlzhczsj": 1351150560000,
		"lastczr": null,
		"zlqzz": null,
		"zlwxyy": null,
		"zlzy": null,
		"zlpz": "F-1-27",
		"zlsfgk": "0",
		"zlfbrq": 1351150560000,
		"zlcxyy": null,
		"zlnzoa": null,
		"zloaid": null,
		"zldq": "00000000",
		"zldqmc": "中华人民共和国",
		"zlfwzg": null,
		"zlsfdl": "0",
		"zlsfzcyh": "0",
		"zldxlx": "00000000000000000000003",
		"zldqbbh": "00000000000000000142651001",
		"zldffg": null,
		"zlxf": null,
		"zlywczr": null,
		"zltypemc": "税收法规->财务会计",
		"zlhytypemc": "通用政策",
		"zlfz": 8,
		"zlisdel": "0",
		"zlwzfgbh": null,
		"zldxlxmc": "全部",
		"zlcxlcid": null,
		"gxsj": null,
		"bbh": null,
		"jhzt": "1",
		"xzqh": "000000000",
		"zlcxsqr": null,
		"zldlssid": "0",
		"zldlxh": null,
		"zlsxczbs": null,
		"zlsfjs": "0",
		"zlsfzjsh": "1",
		"zlzgdw": null,
		"zlzgdwmc": null
	}, {
		"zlcode": "0000000002010102723458",
		"zlwfid": null,
		"activityid": null,
		"zljm": "25702",
		"zltitle": "财政部关于发布《事业单位会计制度》的通知",
		"zlgjz": " 事业单位 会计制度",
		"zlflag": "1",
		"zltype": "“1“000000000123“",
		"zlhytype": "00000000000000000000040",
		"zllywj": "0000000002010102723458.voc",
		"zlczwj": null,
		"zllrr": "总局超管",
		"zllrsj": "2012-10-25",
		"zllrdw": null,
		"zlzt": "60",
		"zlsfyx": "0",
		"zlsffb": "1",
		"zlfbr": "system",
		"zlly": null,
		"zlsz": "0",
		"zlwh": "财预字〔1997〕288号",
		"zlfwdw": "财政部",
		"zlbfrq": 869122096000,
		"zlsxrq": null,
		"zlssrq": 883637296000,
		"zlwjdj": "3",
		"zlsydj": "0",
		"zlnowshr": null,
		"zlnowshjs": null,
		"zlnowjg": null,
		"zlnowbm": null,
		"zlzhczr": "zjsh",
		"zlzhczsj": 1351150527000,
		"lastczr": null,
		"zlqzz": null,
		"zlwxyy": null,
		"zlzy": null,
		"zlpz": "F-1-29",
		"zlsfgk": "0",
		"zlfbrq": 1351150527000,
		"zlcxyy": null,
		"zlnzoa": null,
		"zloaid": null,
		"zldq": "00000000",
		"zldqmc": "中华人民共和国",
		"zlfwzg": null,
		"zlsfdl": "0",
		"zlsfzcyh": "0",
		"zldxlx": "00000000000000000000003",
		"zldqbbh": "00000000000000000142653001",
		"zldffg": null,
		"zlxf": null,
		"zlywczr": null,
		"zltypemc": "税收法规->财务会计",
		"zlhytypemc": "通用政策",
		"zlfz": 29,
		"zlisdel": "0",
		"zlwzfgbh": null,
		"zldxlxmc": "全部",
		"zlcxlcid": null,
		"gxsj": null,
		"bbh": null,
		"jhzt": "1",
		"xzqh": "000000000",
		"zlcxsqr": null,
		"zldlssid": "0",
		"zldlxh": null,
		"zlsxczbs": null,
		"zlsfjs": "0",
		"zlsfzjsh": "1",
		"zlzgdw": null,
		"zlzgdwmc": null
	}, {
		"zlcode": "0000000002010102723457",
		"zlwfid": null,
		"activityid": null,
		"zljm": "25701",
		"zltitle": "事业单位会计准则（试行）",
		"zlgjz": "会计核算 资产 负债 净资产 收入 支出 会计报表 ",
		"zlflag": "1",
		"zltype": "“1“000000000123“",
		"zlhytype": "00000000000000000000040",
		"zllywj": "0000000002010102723457.voc",
		"zlczwj": null,
		"zllrr": "总局超管",
		"zllrsj": "2012-10-25",
		"zllrdw": null,
		"zlzt": "60",
		"zlsfyx": "0",
		"zlsffb": "1",
		"zlfbr": "system",
		"zlly": null,
		"zlsz": "0",
		"zlwh": "财预字〔1997〕286号文件",
		"zlfwdw": "财政部",
		"zlbfrq": 864801989000,
		"zlsxrq": null,
		"zlssrq": 883637189000,
		"zlwjdj": "3",
		"zlsydj": "0",
		"zlnowshr": null,
		"zlnowshjs": null,
		"zlnowjg": null,
		"zlnowbm": null,
		"zlzhczr": "zjsh",
		"zlzhczsj": 1351150419000,
		"lastczr": null,
		"zlqzz": null,
		"zlwxyy": null,
		"zlzy": null,
		"zlpz": "F-1-28",
		"zlsfgk": "0",
		"zlfbrq": 1351150419000,
		"zlcxyy": null,
		"zlnzoa": null,
		"zloaid": null,
		"zldq": "00000000",
		"zldqmc": "中华人民共和国",
		"zlfwzg": null,
		"zlsfdl": "0",
		"zlsfzcyh": "0",
		"zldxlx": "00000000000000000000003",
		"zldqbbh": "00000000000000000142652001",
		"zldffg": null,
		"zlxf": null,
		"zlywczr": null,
		"zltypemc": "税收法规->财务会计",
		"zlhytypemc": "通用政策",
		"zlfz": 8,
		"zlisdel": "0",
		"zlwzfgbh": null,
		"zldxlxmc": "全部",
		"zlcxlcid": null,
		"gxsj": null,
		"bbh": null,
		"jhzt": "1",
		"xzqh": "000000000",
		"zlcxsqr": null,
		"zldlssid": "0",
		"zldlxh": null,
		"zlsxczbs": null,
		"zlsfjs": "0",
		"zlsfzjsh": "1",
		"zlzgdw": null,
		"zlzgdwmc": null
	}, {
		"zlcode": "0000000002010102723447",
		"zlwfid": null,
		"activityid": null,
		"zljm": "25691",
		"zltitle": "企业会计准则",
		"zlgjz": "企业会计准则",
		"zlflag": "1",
		"zltype": "“1“000000000123“",
		"zlhytype": "00000000000000000000040",
		"zllywj": "0000000002010102723447.voc",
		"zlczwj": null,
		"zllrr": "总局超管",
		"zllrsj": "2012-10-25",
		"zllrdw": null,
		"zlzt": "60",
		"zlsfyx": "0",
		"zlsffb": "1",
		"zlfbr": "system",
		"zlly": null,
		"zlsz": "0",
		"zlwh": "财政部发布",
		"zlfwdw": "财政部",
		"zlbfrq": 723105952000,
		"zlsxrq": null,
		"zlssrq": 741509152000,
		"zlwjdj": "3",
		"zlsydj": "0",
		"zlnowshr": null,
		"zlnowshjs": null,
		"zlnowjg": null,
		"zlnowbm": null,
		"zlzhczr": "zjsh",
		"zlzhczsj": 1351150382000,
		"lastczr": null,
		"zlqzz": null,
		"zlwxyy": null,
		"zlzy": null,
		"zlpz": "F-1-3",
		"zlsfgk": "0",
		"zlfbrq": 1351150382000,
		"zlcxyy": null,
		"zlnzoa": null,
		"zloaid": null,
		"zldq": "00000000",
		"zldqmc": "中华人民共和国",
		"zlfwzg": null,
		"zlsfdl": "0",
		"zlsfzcyh": "0",
		"zldxlx": "00000000000000000000003",
		"zldqbbh": "00000000000000000142642001",
		"zldffg": null,
		"zlxf": null,
		"zlywczr": null,
		"zltypemc": "税收法规->财务会计",
		"zlhytypemc": "通用政策",
		"zlfz": 9,
		"zlisdel": "0",
		"zlwzfgbh": null,
		"zldxlxmc": "全部",
		"zlcxlcid": null,
		"gxsj": null,
		"bbh": null,
		"jhzt": "1",
		"xzqh": "000000000",
		"zlcxsqr": null,
		"zldlssid": "0",
		"zldlxh": null,
		"zlsxczbs": null,
		"zlsfjs": "0",
		"zlsfzjsh": "1",
		"zlzgdw": null,
		"zlzgdwmc": null
	}, {
		"zlcode": "0000000002010102723446",
		"zlwfid": null,
		"activityid": null,
		"zljm": "25690",
		"zltitle": "企业财务通则",
		"zlgjz": "企业财务通则",
		"zlflag": "1",
		"zltype": "“1“000000000123“",
		"zlhytype": "00000000000000000000040",
		"zllywj": "0000000002010102723446.voc",
		"zlczwj": null,
		"zllrr": "总局超管",
		"zllrsj": "2012-10-25",
		"zllrdw": null,
		"zlzt": "60",
		"zlsfyx": "0",
		"zlsffb": "1",
		"zlfbr": "system",
		"zlly": null,
		"zlsz": "0",
		"zlwh": "1992年11月30日财政部发布",
		"zlfwdw": "财政部",
		"zlbfrq": 723105912000,
		"zlsxrq": null,
		"zlssrq": 741509112000,
		"zlwjdj": "3",
		"zlsydj": "0",
		"zlnowshr": null,
		"zlnowshjs": null,
		"zlnowjg": null,
		"zlnowbm": null,
		"zlzhczr": "zjsh",
		"zlzhczsj": 1351150342000,
		"lastczr": null,
		"zlqzz": null,
		"zlwxyy": null,
		"zlzy": null,
		"zlpz": "F-1-2",
		"zlsfgk": "0",
		"zlfbrq": 1351150343000,
		"zlcxyy": null,
		"zlnzoa": null,
		"zloaid": null,
		"zldq": "00000000",
		"zldqmc": "中华人民共和国",
		"zlfwzg": null,
		"zlsfdl": "0",
		"zlsfzcyh": "0",
		"zldxlx": "00000000000000000000003",
		"zldqbbh": "00000000000000000142641001",
		"zldffg": null,
		"zlxf": null,
		"zlywczr": null,
		"zltypemc": "税收法规->财务会计",
		"zlhytypemc": "通用政策",
		"zlfz": 89,
		"zlisdel": "0",
		"zlwzfgbh": null,
		"zldxlxmc": "全部",
		"zlcxlcid": null,
		"gxsj": null,
		"bbh": null,
		"jhzt": "1",
		"xzqh": "000000000",
		"zlcxsqr": null,
		"zldlssid": "0",
		"zldlxh": null,
		"zlsxczbs": null,
		"zlsfjs": "0",
		"zlsfzjsh": "1",
		"zlzgdw": null,
		"zlzgdwmc": null
	}, {
		"zlcode": "0000000002010102723468",
		"zlwfid": null,
		"activityid": null,
		"zljm": "25712",
		"zltitle": "金融企业会计制度",
		"zlgjz": "金融企业 会计制度",
		"zlflag": "1",
		"zltype": "“1“000000000123“00000000012301“",
		"zlhytype": "00000000000000000000040",
		"zllywj": "0000000002010102723468.voc",
		"zlczwj": null,
		"zllrr": "总局超管",
		"zllrsj": "2012-10-25",
		"zllrdw": null,
		"zlzt": "60",
		"zlsfyx": "1",
		"zlsffb": "1",
		"zlfbr": "system",
		"zlly": null,
		"zlsz": "0",
		"zlwh": "财会〔2001〕49号",
		"zlfwdw": "财政部",
		"zlbfrq": 1006843451000,
		"zlsxrq": 1298270651000,
		"zlssrq": 1009867451000,
		"zlwjdj": "3",
		"zlsydj": "0",
		"zlnowshr": null,
		"zlnowshjs": null,
		"zlnowjg": null,
		"zlnowbm": null,
		"zlzhczr": "zjsh",
		"zlzhczsj": 1351150282000,
		"lastczr": null,
		"zlqzz": null,
		"zlwxyy": "全文废止。根据：《财政部关于公布废止和失效的财政规章和规范性文件目录（第十一批）的决定》（中华人民共和国财政部令第62号，2011.02.21）。",
		"zlzy": null,
		"zlpz": "F-1-42",
		"zlsfgk": "0",
		"zlfbrq": 1351150282000,
		"zlcxyy": null,
		"zlnzoa": null,
		"zloaid": null,
		"zldq": "00000000",
		"zldqmc": "中华人民共和国",
		"zlfwzg": null,
		"zlsfdl": "0",
		"zlsfzcyh": "0",
		"zldxlx": "00000000000000000000003",
		"zldqbbh": "00000000000000000142663002",
		"zldffg": null,
		"zlxf": null,
		"zlywczr": null,
		"zltypemc": "税收法规->财务会计->会计法规制度",
		"zlhytypemc": "通用政策",
		"zlfz": 34,
		"zlisdel": "0",
		"zlwzfgbh": null,
		"zldxlxmc": "全部",
		"zlcxlcid": null,
		"gxsj": null,
		"bbh": null,
		"jhzt": "1",
		"xzqh": "000000000",
		"zlcxsqr": null,
		"zldlssid": "0",
		"zldlxh": null,
		"zlsxczbs": null,
		"zlsfjs": "0",
		"zlsfzjsh": "1",
		"zlzgdw": null,
		"zlzgdwmc": null
	}, {
		"zlcode": "0000000002010102723467",
		"zlwfid": null,
		"activityid": null,
		"zljm": "25711",
		"zltitle": "企业会计制度",
		"zlgjz": "企业 会计制度",
		"zlflag": "1",
		"zltype": "“1“000000000123“00000000012301“",
		"zlhytype": "00000000000000000000040",
		"zllywj": "0000000002010102723467.voc",
		"zlczwj": null,
		"zllrr": "总局超管",
		"zllrsj": "2012-10-25",
		"zllrdw": null,
		"zlzt": "60",
		"zlsfyx": "0",
		"zlsffb": "1",
		"zlfbr": "system",
		"zlly": null,
		"zlsz": "0",
		"zlwh": "财会〔2000〕25号",
		"zlfwdw": "财政部",
		"zlbfrq": 978072217000,
		"zlsxrq": null,
		"zlssrq": 978331417000,
		"zlwjdj": "3",
		"zlsydj": "0",
		"zlnowshr": null,
		"zlnowshjs": null,
		"zlnowjg": null,
		"zlnowbm": null,
		"zlzhczr": "zjsh",
		"zlzhczsj": 1351150248000,
		"lastczr": null,
		"zlqzz": null,
		"zlwxyy": null,
		"zlzy": null,
		"zlpz": "F-1-41",
		"zlsfgk": "0",
		"zlfbrq": 1351150248000,
		"zlcxyy": null,
		"zlnzoa": null,
		"zloaid": null,
		"zldq": "00000000",
		"zldqmc": "中华人民共和国",
		"zlfwzg": null,
		"zlsfdl": "0",
		"zlsfzcyh": "0",
		"zldxlx": "00000000000000000000003",
		"zldqbbh": "00000000000000000142662001",
		"zldffg": null,
		"zlxf": null,
		"zlywczr": null,
		"zltypemc": "税收法规->财务会计->会计法规制度",
		"zlhytypemc": "通用政策",
		"zlfz": 162,
		"zlisdel": "0",
		"zlwzfgbh": null,
		"zldxlxmc": "全部",
		"zlcxlcid": null,
		"gxsj": null,
		"bbh": null,
		"jhzt": "1",
		"xzqh": "000000000",
		"zlcxsqr": null,
		"zldlssid": "0",
		"zldlxh": null,
		"zlsxczbs": null,
		"zlsfjs": "0",
		"zlsfzjsh": "1",
		"zlzgdw": null,
		"zlzgdwmc": null
	}, {
		"zlcode": "0000000002010102723128",
		"zlwfid": null,
		"activityid": null,
		"zljm": "25372",
		"zltitle": "财政部关于企业收到政府拨给的搬迁补偿款有关财务处理问题的通知",
		"zlgjz": " 搬迁 补偿款 财务处理",
		"zlflag": "1",
		"zltype": "“1“000000000123“,“1“000000000106“",
		"zlhytype": "00000000000000000000040",
		"zllywj": "0000000002010102723128.voc",
		"zlczwj": null,
		"zllrr": "总局超管",
		"zllrsj": "2012-10-24",
		"zllrdw": null,
		"zlzt": "60",
		"zlsfyx": "0",
		"zlsffb": "1",
		"zlfbr": "system",
		"zlly": null,
		"zlsz": "0",
		"zlwh": "财企〔2005〕123号",
		"zlfwdw": "财政部",
		"zlbfrq": 1124085816000,
		"zlsxrq": null,
		"zlssrq": 1124085816000,
		"zlwjdj": "3",
		"zlsydj": "0",
		"zlnowshr": null,
		"zlnowshjs": null,
		"zlnowjg": null,
		"zlnowbm": null,
		"zlzhczr": "zjsh",
		"zlzhczsj": 1351061333000,
		"lastczr": null,
		"zlqzz": null,
		"zlwxyy": null,
		"zlzy": null,
		"zlpz": "7-2-132",
		"zlsfgk": "0",
		"zlfbrq": 1351061333000,
		"zlcxyy": null,
		"zlnzoa": null,
		"zloaid": null,
		"zldq": "00000000",
		"zldqmc": "中华人民共和国",
		"zlfwzg": null,
		"zlsfdl": "0",
		"zlsfzcyh": "0",
		"zldxlx": "00000000000000000000001",
		"zldqbbh": "00000000000000000142323001",
		"zldffg": null,
		"zlxf": null,
		"zlywczr": null,
		"zltypemc": "税收法规->企业所得税；税收法规->财务会计",
		"zlhytypemc": "通用政策",
		"zlfz": 51,
		"zlisdel": "0",
		"zlwzfgbh": null,
		"zldxlxmc": "单位",
		"zlcxlcid": null,
		"gxsj": null,
		"bbh": null,
		"jhzt": "1",
		"xzqh": "000000000",
		"zlcxsqr": null,
		"zldlssid": "0",
		"zldlxh": null,
		"zlsxczbs": null,
		"zlsfjs": "0",
		"zlsfzjsh": "1",
		"zlzgdw": null,
		"zlzgdwmc": null
	}, {
		"zlcode": "0000000002010102721972",
		"zlwfid": null,
		"activityid": null,
		"zljm": "24216",
		"zltitle": "财政部关于印发《农业税收征解会计制度》的通知",
		"zlgjz": "农业税收 征解 会计 制度",
		"zlflag": "1",
		"zltype": "“1“000000000123“,“1“000000000126“00000000012607“,“1“000000000118“,“1“000000000126“00000000012608“,“1“000000000117“,“1“000000000126“00000000012609“",
		"zlhytype": "00000000000000000000040",
		"zllywj": "0000000002010102721972.voc",
		"zlczwj": null,
		"zllrr": "总局超管",
		"zllrsj": "2012-10-20",
		"zllrdw": null,
		"zlzt": "60",
		"zlsfyx": "1",
		"zlsffb": "1",
		"zlfbr": "system",
		"zlly": null,
		"zlsz": "0",
		"zlwh": "（1992）财农税字第46号",
		"zlfwdw": "财政部",
		"zlbfrq": 717300492000,
		"zlsxrq": 915156492000,
		"zlssrq": 725854092000,
		"zlwjdj": "3",
		"zlsydj": "0",
		"zlnowshr": null,
		"zlnowshjs": null,
		"zlnowjg": null,
		"zlnowbm": null,
		"zlzhczr": "zjsh",
		"zlzhczsj": 1350701587000,
		"lastczr": null,
		"zlqzz": null,
		"zlwxyy": "全文废止。根据：《国家税务总局关于印发农业税收会计制度的通知》，国税发〔1998〕216号。\n\n",
		"zlzy": null,
		"zlpz": "F-1-1",
		"zlsfgk": "0",
		"zlfbrq": 1350701587000,
		"zlcxyy": null,
		"zlnzoa": null,
		"zloaid": null,
		"zldq": "00000000",
		"zldqmc": "中华人民共和国",
		"zlfwzg": null,
		"zlsfdl": "0",
		"zlsfzcyh": "0",
		"zldxlx": "00000000000000000000003",
		"zldqbbh": "00000000000000000141167001",
		"zldffg": null,
		"zlxf": null,
		"zlywczr": null,
		"zltypemc": "税收法规->停征税种->牧业税；税收法规->耕地占用税；税收法规->停征税种->农业特产税；税收法规->契税；税收法规->停征税种->农业税；税收法规->财务会计",
		"zlhytypemc": "通用政策",
		"zlfz": 8,
		"zlisdel": "0",
		"zlwzfgbh": null,
		"zldxlxmc": "全部",
		"zlcxlcid": null,
		"gxsj": null,
		"bbh": null,
		"jhzt": "1",
		"xzqh": "000000000",
		"zlcxsqr": null,
		"zldlssid": "0",
		"zldlxh": null,
		"zlsxczbs": null,
		"zlsfjs": "0",
		"zlsfzjsh": "1",
		"zlzgdw": null,
		"zlzgdwmc": null
	}, {
		"zlcode": "0000000002010111500333",
		"zlwfid": null,
		"activityid": null,
		"zljm": "20925",
		"zltitle": "财政部关于中央行政事业单位所属企业国有资产监管工作归口管理的通知",
		"zlgjz": "中央行政事业单位  企业国有资产监管 工作归口管理",
		"zlflag": "1",
		"zltype": "“1“000000000123“",
		"zlhytype": "00000000000000000000040",
		"zllywj": "0000000002010111500333.voc",
		"zlczwj": null,
		"zllrr": "ssfgcj10",
		"zllrsj": "2012-10-17",
		"zllrdw": "第七运维中心",
		"zlzt": "60",
		"zlsfyx": "0",
		"zlsffb": "1",
		"zlfbr": "system",
		"zlly": null,
		"zlsz": "0",
		"zlwh": "财办〔2010〕35号",
		"zlfwdw": "财政部",
		"zlbfrq": 1282788078000,
		"zlsxrq": null,
		"zlssrq": null,
		"zlwjdj": "3",
		"zlsydj": "0",
		"zlnowshr": null,
		"zlnowshjs": null,
		"zlnowjg": null,
		"zlnowbm": null,
		"zlzhczr": "zjsh",
		"zlzhczsj": 1350441957000,
		"lastczr": null,
		"zlqzz": null,
		"zlwxyy": null,
		"zlzy": null,
		"zlpz": "2010-10",
		"zlsfgk": "0",
		"zlfbrq": 1350441957000,
		"zlcxyy": null,
		"zlnzoa": null,
		"zloaid": null,
		"zldq": "00000000",
		"zldqmc": "中华人民共和国",
		"zlfwzg": null,
		"zlsfdl": "0",
		"zlsfzcyh": "0",
		"zldxlx": "00000000000000000000001",
		"zldqbbh": "1970000002010111500333001",
		"zldffg": null,
		"zlxf": null,
		"zlywczr": null,
		"zltypemc": "税收法规->财务会计",
		"zlhytypemc": "通用政策",
		"zlfz": 12,
		"zlisdel": "0",
		"zlwzfgbh": null,
		"zldxlxmc": "单位",
		"zlcxlcid": null,
		"gxsj": null,
		"bbh": null,
		"jhzt": "1",
		"xzqh": "000000000",
		"zlcxsqr": null,
		"zldlssid": "0",
		"zldlxh": null,
		"zlsxczbs": "0",
		"zlsfjs": "0",
		"zlsfzjsh": "1",
		"zlzgdw": null,
		"zlzgdwmc": null
	}, {
		"zlcode": "0000000002010111300039",
		"zlwfid": null,
		"activityid": null,
		"zljm": "20475",
		"zltitle": "财政部关于印发《会计师事务所财务管理暂行办法》的通知",
		"zlgjz": "会计师事务所 财务管理",
		"zlflag": "1",
		"zltype": "“1“000000000123“",
		"zlhytype": "00000000000000000000032",
		"zllywj": "0000000002010111300039.voc",
		"zlczwj": null,
		"zllrr": "ssfgcj10",
		"zllrsj": "2012-10-17",
		"zllrdw": "第七运维中心",
		"zlzt": "60",
		"zlsfyx": "0",
		"zlsffb": "1",
		"zlfbr": "system",
		"zlly": null,
		"zlsz": "0",
		"zlwh": "财会〔2010〕14号",
		"zlfwdw": "财政部",
		"zlbfrq": 1276394458000,
		"zlsxrq": null,
		"zlssrq": 1293847258000,
		"zlwjdj": "3",
		"zlsydj": "0",
		"zlnowshr": null,
		"zlnowshjs": null,
		"zlnowjg": null,
		"zlnowbm": null,
		"zlzhczr": "zjsh",
		"zlzhczsj": 1350441937000,
		"lastczr": null,
		"zlqzz": null,
		"zlwxyy": null,
		"zlzy": null,
		"zlpz": "F-2-6",
		"zlsfgk": "0",
		"zlfbrq": 1350441937000,
		"zlcxyy": null,
		"zlnzoa": null,
		"zloaid": null,
		"zldq": "00000000",
		"zldqmc": "中华人民共和国",
		"zlfwzg": null,
		"zlsfdl": "0",
		"zlsfzcyh": "0",
		"zldxlx": "00000000000000000000003",
		"zldqbbh": "1970000002010111300039001",
		"zldffg": null,
		"zlxf": null,
		"zlywczr": null,
		"zltypemc": "税收法规->财务会计",
		"zlhytypemc": "代理业",
		"zlfz": 10,
		"zlisdel": "0",
		"zlwzfgbh": null,
		"zldxlxmc": "全部",
		"zlcxlcid": null,
		"gxsj": null,
		"bbh": null,
		"jhzt": "1",
		"xzqh": "000000000",
		"zlcxsqr": null,
		"zldlssid": "0",
		"zldlxh": null,
		"zlsxczbs": "0",
		"zlsfjs": "0",
		"zlsfzjsh": "1",
		"zlzgdw": null,
		"zlzgdwmc": null
	}, {
		"zlcode": "0000000002010102726625",
		"zlwfid": null,
		"activityid": null,
		"zljm": "28869",
		"zltitle": "财政部关于中央行政事业单位资金往来结算票据使用管理等有关问题的通知",
		"zlgjz": "中央 行政 事业单位 资金往来 票据 管理",
		"zlflag": "1",
		"zltype": "“1“000000000123“",
		"zlhytype": "00000000000000000000040",
		"zllywj": "0000000002010102726625.voc",
		"zlczwj": null,
		"zllrr": "总局超管",
		"zllrsj": "2012-10-17",
		"zllrdw": null,
		"zlzt": "60",
		"zlsfyx": "0",
		"zlsffb": "1",
		"zlfbr": "system",
		"zlly": null,
		"zlsz": "0",
		"zlwh": "财综〔2010〕7号",
		"zlfwdw": "财政部",
		"zlbfrq": 1264643963000,
		"zlsxrq": null,
		"zlssrq": null,
		"zlwjdj": "3",
		"zlsydj": "0",
		"zlnowshr": null,
		"zlnowshjs": null,
		"zlnowjg": null,
		"zlnowbm": null,
		"zlzhczr": "zjsh",
		"zlzhczsj": 1350441842000,
		"lastczr": null,
		"zlqzz": null,
		"zlwxyy": null,
		"zlzy": null,
		"zlpz": "1-4-94",
		"zlsfgk": "0",
		"zlfbrq": 1350441842000,
		"zlcxyy": null,
		"zlnzoa": null,
		"zloaid": null,
		"zldq": "00000000",
		"zldqmc": "中华人民共和国",
		"zlfwzg": null,
		"zlsfdl": "0",
		"zlsfzcyh": "0",
		"zldxlx": "00000000000000000000003",
		"zldqbbh": "00000000000000000145820001",
		"zldffg": null,
		"zlxf": null,
		"zlywczr": null,
		"zltypemc": "税收法规->财务会计",
		"zlhytypemc": "通用政策",
		"zlfz": 29,
		"zlisdel": "0",
		"zlwzfgbh": null,
		"zldxlxmc": "全部",
		"zlcxlcid": null,
		"gxsj": null,
		"bbh": null,
		"jhzt": "1",
		"xzqh": "000000000",
		"zlcxsqr": null,
		"zldlssid": "0",
		"zldlxh": null,
		"zlsxczbs": null,
		"zlsfjs": "0",
		"zlsfzjsh": "1",
		"zlzgdw": null,
		"zlzgdwmc": null
	}, {
		"zlcode": "0000000002010102726612",
		"zlwfid": null,
		"activityid": null,
		"zljm": "28856",
		"zltitle": "财政部关于印发《非上市银行业金融机构执行〈企业会计准则〉有关衔接规定》的通知",
		"zlgjz": "非上市 银行业金融机构 执行 企业会计准则 衔接规定",
		"zlflag": "1",
		"zltype": "“1“000000000123“",
		"zlhytype": "00000000000000000000040",
		"zllywj": "0000000002010102726612.voc",
		"zlczwj": null,
		"zllrr": "总局超管",
		"zllrsj": "2012-10-17",
		"zllrdw": null,
		"zlzt": "60",
		"zlsfyx": "0",
		"zlsffb": "1",
		"zlfbr": "system",
		"zlly": null,
		"zlsz": "0",
		"zlwh": "财会〔2007〕16号",
		"zlfwdw": "财政部",
		"zlbfrq": 1198893539000,
		"zlsxrq": null,
		"zlssrq": null,
		"zlwjdj": "3",
		"zlsydj": "0",
		"zlnowshr": null,
		"zlnowshjs": null,
		"zlnowjg": null,
		"zlnowbm": null,
		"zlzhczr": "zjsh",
		"zlzhczsj": 1350441818000,
		"lastczr": null,
		"zlqzz": null,
		"zlwxyy": null,
		"zlzy": null,
		"zlpz": "F-1-70",
		"zlsfgk": "0",
		"zlfbrq": 1350441818000,
		"zlcxyy": null,
		"zlnzoa": null,
		"zloaid": null,
		"zldq": "00000000",
		"zldqmc": "中华人民共和国",
		"zlfwzg": null,
		"zlsfdl": "0",
		"zlsfzcyh": "0",
		"zldxlx": "00000000000000000000003",
		"zldqbbh": "00000000000000000145807001",
		"zldffg": null,
		"zlxf": null,
		"zlywczr": null,
		"zltypemc": "税收法规->财务会计",
		"zlhytypemc": "通用政策",
		"zlfz": 0,
		"zlisdel": "0",
		"zlwzfgbh": null,
		"zldxlxmc": "全部",
		"zlcxlcid": null,
		"gxsj": null,
		"bbh": null,
		"jhzt": "1",
		"xzqh": "000000000",
		"zlcxsqr": null,
		"zldlssid": "0",
		"zldlxh": null,
		"zlsxczbs": null,
		"zlsfjs": "0",
		"zlsfzjsh": "1",
		"zlzgdw": null,
		"zlzgdwmc": null
	}, {
		"zlcode": "0000000002010102726611",
		"zlwfid": null,
		"activityid": null,
		"zljm": "28855",
		"zltitle": "财政部关于进一步加强金融企业财务管理若干问题的通知",
		"zlgjz": "金融企业 财务管理 ",
		"zlflag": "1",
		"zltype": "“1“000000000123“00000000012302“",
		"zlhytype": "00000000000000000000040",
		"zllywj": "0000000002010102726611.voc",
		"zlczwj": null,
		"zllrr": "总局超管",
		"zllrsj": "2012-10-17",
		"zllrdw": null,
		"zlzt": "60",
		"zlsfyx": "0",
		"zlsffb": "1",
		"zlfbr": "system",
		"zlly": null,
		"zlsz": "0",
		"zlwh": "财金〔2008〕12号",
		"zlfwdw": "财政部",
		"zlbfrq": 1202867909000,
		"zlsxrq": null,
		"zlssrq": null,
		"zlwjdj": "3",
		"zlsydj": "0",
		"zlnowshr": null,
		"zlnowshjs": null,
		"zlnowjg": null,
		"zlnowbm": null,
		"zlzhczr": "zjsh",
		"zlzhczsj": 1350441789000,
		"lastczr": null,
		"zlqzz": null,
		"zlwxyy": null,
		"zlzy": null,
		"zlpz": "F-1-71",
		"zlsfgk": "0",
		"zlfbrq": 1350441789000,
		"zlcxyy": null,
		"zlnzoa": null,
		"zloaid": null,
		"zldq": "00000000",
		"zldqmc": "中华人民共和国",
		"zlfwzg": null,
		"zlsfdl": "0",
		"zlsfzcyh": "0",
		"zldxlx": "00000000000000000000003",
		"zldqbbh": "00000000000000000145806001",
		"zldffg": null,
		"zlxf": null,
		"zlywczr": null,
		"zltypemc": "税收法规->财务会计->企业财务管理",
		"zlhytypemc": "通用政策",
		"zlfz": 66,
		"zlisdel": "0",
		"zlwzfgbh": null,
		"zldxlxmc": "全部",
		"zlcxlcid": null,
		"gxsj": null,
		"bbh": null,
		"jhzt": "1",
		"xzqh": "000000000",
		"zlcxsqr": null,
		"zldlssid": "0",
		"zldlxh": null,
		"zlsxczbs": null,
		"zlsfjs": "0",
		"zlsfzjsh": "1",
		"zlzgdw": null,
		"zlzgdwmc": null
	}, {
		"zlcode": "0000000002010102726610",
		"zlwfid": null,
		"activityid": null,
		"zljm": "28854",
		"zltitle": "财政部关于企业新旧财务制度衔接有关问题的通知",
		"zlgjz": "补充养老保险 费用列支 工资 结余处理 ",
		"zlflag": "1",
		"zltype": "“1“000000000123“",
		"zlhytype": "00000000000000000000040",
		"zllywj": "0000000002010102726610.voc",
		"zlczwj": null,
		"zllrr": "总局超管",
		"zllrsj": "2012-10-17",
		"zllrdw": null,
		"zlzt": "60",
		"zlsfyx": "0",
		"zlsffb": "1",
		"zlfbr": "system",
		"zlly": null,
		"zlsz": "0",
		"zlwh": "财企〔2008〕34号",
		"zlfwdw": "财政部",
		"zlbfrq": 1204250286000,
		"zlsxrq": null,
		"zlssrq": null,
		"zlwjdj": "3",
		"zlsydj": "0",
		"zlnowshr": null,
		"zlnowshjs": null,
		"zlnowjg": null,
		"zlnowbm": null,
		"zlzhczr": "zjsh",
		"zlzhczsj": 1350441766000,
		"lastczr": null,
		"zlqzz": null,
		"zlwxyy": null,
		"zlzy": null,
		"zlpz": "F-1-72",
		"zlsfgk": "0",
		"zlfbrq": 1350441766000,
		"zlcxyy": null,
		"zlnzoa": null,
		"zloaid": null,
		"zldq": "00000000",
		"zldqmc": "中华人民共和国",
		"zlfwzg": null,
		"zlsfdl": "0",
		"zlsfzcyh": "0",
		"zldxlx": "00000000000000000000003",
		"zldqbbh": "00000000000000000145805001",
		"zldffg": null,
		"zlxf": null,
		"zlywczr": null,
		"zltypemc": "税收法规->财务会计",
		"zlhytypemc": "通用政策",
		"zlfz": 28,
		"zlisdel": "0",
		"zlwzfgbh": null,
		"zldxlxmc": "全部",
		"zlcxlcid": null,
		"gxsj": null,
		"bbh": null,
		"jhzt": "1",
		"xzqh": "000000000",
		"zlcxsqr": null,
		"zldlssid": "0",
		"zldlxh": null,
		"zlsxczbs": null,
		"zlsfjs": "0",
		"zlsfzjsh": "1",
		"zlzgdw": null,
		"zlzgdwmc": null
	}, {
		"zlcode": "0000000002010102726609",
		"zlwfid": null,
		"activityid": null,
		"zljm": "28853",
		"zltitle": "财政部关于印发《企业会计准则解释第2号》的通知",
		"zlgjz": "企业会计准则 解释 第2号",
		"zlflag": "1",
		"zltype": "“1“000000000123“",
		"zlhytype": "00000000000000000000040",
		"zllywj": "0000000002010102726609.voc",
		"zlczwj": null,
		"zllrr": "总局超管",
		"zllrsj": "2012-10-17",
		"zllrdw": null,
		"zlzt": "60",
		"zlsfyx": "0",
		"zlsffb": "1",
		"zlfbr": "system",
		"zlly": null,
		"zlsz": "0",
		"zlwh": "财会〔2008〕11号",
		"zlfwdw": "财政部",
		"zlbfrq": 1218074265000,
		"zlsxrq": null,
		"zlssrq": null,
		"zlwjdj": "3",
		"zlsydj": "0",
		"zlnowshr": null,
		"zlnowshjs": null,
		"zlnowjg": null,
		"zlnowbm": null,
		"zlzhczr": "zjsh",
		"zlzhczsj": 1350441745000,
		"lastczr": null,
		"zlqzz": null,
		"zlwxyy": null,
		"zlzy": null,
		"zlpz": "F-1-73",
		"zlsfgk": "0",
		"zlfbrq": 1350441745000,
		"zlcxyy": null,
		"zlnzoa": null,
		"zloaid": null,
		"zldq": "00000000",
		"zldqmc": "中华人民共和国",
		"zlfwzg": null,
		"zlsfdl": "0",
		"zlsfzcyh": "0",
		"zldxlx": "00000000000000000000003",
		"zldqbbh": "00000000000000000145804001",
		"zldffg": null,
		"zlxf": null,
		"zlywczr": null,
		"zltypemc": "税收法规->财务会计",
		"zlhytypemc": "通用政策",
		"zlfz": 84,
		"zlisdel": "0",
		"zlwzfgbh": null,
		"zldxlxmc": "全部",
		"zlcxlcid": null,
		"gxsj": null,
		"bbh": null,
		"jhzt": "1",
		"xzqh": "000000000",
		"zlcxsqr": null,
		"zldlssid": "0",
		"zldlxh": null,
		"zlsxczbs": null,
		"zlsfjs": "0",
		"zlsfzjsh": "1",
		"zlzgdw": null,
		"zlzgdwmc": null
	}, {
		"zlcode": "0000000002010102726608",
		"zlwfid": null,
		"activityid": null,
		"zljm": "28852",
		"zltitle": "财政部关于印发工会会计制度、工会新旧会计制度有关衔接问题的处理规定的通知",
		"zlgjz": "工会 新旧 会计制度 衔接 ",
		"zlflag": "1",
		"zltype": "“1“000000000123“",
		"zlhytype": "00000000000000000000040",
		"zllywj": "0000000002010102726608.voc",
		"zlczwj": null,
		"zllrr": "总局超管",
		"zllrsj": "2012-10-17",
		"zllrdw": null,
		"zlzt": "60",
		"zlsfyx": "0",
		"zlsffb": "1",
		"zlfbr": "system",
		"zlly": null,
		"zlsz": "0",
		"zlwh": "财会〔2009〕7号",
		"zlfwdw": "财政部",
		"zlbfrq": 1243735029000,
		"zlsxrq": null,
		"zlssrq": 1262311029000,
		"zlwjdj": "3",
		"zlsydj": "0",
		"zlnowshr": null,
		"zlnowshjs": null,
		"zlnowjg": null,
		"zlnowbm": null,
		"zlzhczr": "zjsh",
		"zlzhczsj": 1350441708000,
		"lastczr": null,
		"zlqzz": null,
		"zlwxyy": null,
		"zlzy": null,
		"zlpz": "F-1-74",
		"zlsfgk": "0",
		"zlfbrq": 1350441708000,
		"zlcxyy": null,
		"zlnzoa": null,
		"zloaid": null,
		"zldq": "00000000",
		"zldqmc": "中华人民共和国",
		"zlfwzg": null,
		"zlsfdl": "0",
		"zlsfzcyh": "0",
		"zldxlx": "00000000000000000000003",
		"zldqbbh": "00000000000000000145803001",
		"zldffg": null,
		"zlxf": null,
		"zlywczr": null,
		"zltypemc": "税收法规->财务会计",
		"zlhytypemc": "通用政策",
		"zlfz": 11,
		"zlisdel": "0",
		"zlwzfgbh": null,
		"zldxlxmc": "全部",
		"zlcxlcid": null,
		"gxsj": null,
		"bbh": null,
		"jhzt": "1",
		"xzqh": "000000000",
		"zlcxsqr": null,
		"zldlssid": "0",
		"zldlxh": null,
		"zlsxczbs": null,
		"zlsfjs": "0",
		"zlsfzjsh": "1",
		"zlzgdw": null,
		"zlzgdwmc": null
	}, {
		"zlcode": "0000000002010102726607",
		"zlwfid": null,
		"activityid": null,
		"zljm": "28851",
		"zltitle": "财政部关于印发企业会计准则解释第3号的通知",
		"zlgjz": "企业会计准则 解释 第3号",
		"zlflag": "1",
		"zltype": "“1“000000000123“",
		"zlhytype": "00000000000000000000040",
		"zllywj": "0000000002010102726607.voc",
		"zlczwj": null,
		"zllrr": "总局超管",
		"zllrsj": "2012-10-17",
		"zllrdw": null,
		"zlzt": "60",
		"zlsfyx": "0",
		"zlsffb": "1",
		"zlfbr": "system",
		"zlly": null,
		"zlsz": "0",
		"zlwh": "财会〔2009〕8号",
		"zlfwdw": "财政部",
		"zlbfrq": 1244685404000,
		"zlsxrq": null,
		"zlssrq": null,
		"zlwjdj": "3",
		"zlsydj": "0",
		"zlnowshr": null,
		"zlnowshjs": null,
		"zlnowjg": null,
		"zlnowbm": null,
		"zlzhczr": "zjsh",
		"zlzhczsj": 1350441683000,
		"lastczr": null,
		"zlqzz": null,
		"zlwxyy": null,
		"zlzy": null,
		"zlpz": "F-1-75",
		"zlsfgk": "0",
		"zlfbrq": 1350441683000,
		"zlcxyy": null,
		"zlnzoa": null,
		"zloaid": null,
		"zldq": "00000000",
		"zldqmc": "中华人民共和国",
		"zlfwzg": null,
		"zlsfdl": "0",
		"zlsfzcyh": "0",
		"zldxlx": "00000000000000000000003",
		"zldqbbh": "00000000000000000145802001",
		"zldffg": null,
		"zlxf": null,
		"zlywczr": null,
		"zltypemc": "税收法规->财务会计",
		"zlhytypemc": "通用政策",
		"zlfz": 130,
		"zlisdel": "0",
		"zlwzfgbh": null,
		"zldxlxmc": "全部",
		"zlcxlcid": null,
		"gxsj": null,
		"bbh": null,
		"jhzt": "1",
		"xzqh": "000000000",
		"zlcxsqr": null,
		"zldlssid": "0",
		"zldlxh": null,
		"zlsxczbs": null,
		"zlsfjs": "0",
		"zlsfzjsh": "1",
		"zlzgdw": null,
		"zlzgdwmc": null
	}, {
		"zlcode": "0000000002010102726587",
		"zlwfid": null,
		"activityid": null,
		"zljm": "28831",
		"zltitle": "国家税务总局关于开立税务代保管资金账户有关问题的紧急通知",
		"zlgjz": "代保管 资金 账户",
		"zlflag": "1",
		"zltype": "“1“000000000102“,“1“000000000123“",
		"zlhytype": "00000000000000000000040",
		"zllywj": "0000000002010102726587.voc",
		"zlczwj": null,
		"zllrr": "总局超管",
		"zllrsj": "2012-10-17",
		"zllrdw": null,
		"zlzt": "60",
		"zlsfyx": "0",
		"zlsffb": "1",
		"zlfbr": "system",
		"zlly": null,
		"zlsz": "0",
		"zlwh": "国税函〔2006〕755号",
		"zlfwdw": "国家税务总局",
		"zlbfrq": 1155261366000,
		"zlsxrq": null,
		"zlssrq": null,
		"zlwjdj": "3",
		"zlsydj": "0",
		"zlnowshr": null,
		"zlnowshjs": null,
		"zlnowjg": null,
		"zlnowbm": null,
		"zlzhczr": "zjsh",
		"zlzhczsj": 1350441645000,
		"lastczr": null,
		"zlqzz": null,
		"zlwxyy": null,
		"zlzy": null,
		"zlpz": "1-2-64",
		"zlsfgk": "0",
		"zlfbrq": 1350441645000,
		"zlcxyy": null,
		"zlnzoa": null,
		"zloaid": null,
		"zldq": "00000000",
		"zldqmc": "中华人民共和国",
		"zlfwzg": null,
		"zlsfdl": "0",
		"zlsfzcyh": "0",
		"zldxlx": "00000000000000000000003",
		"zldqbbh": "00000000000000000145782001",
		"zldffg": null,
		"zlxf": null,
		"zlywczr": null,
		"zltypemc": "税收法规->财务会计；税收法规->征收管理",
		"zlhytypemc": "通用政策",
		"zlfz": 7,
		"zlisdel": "0",
		"zlwzfgbh": null,
		"zldxlxmc": "全部",
		"zlcxlcid": null,
		"gxsj": null,
		"bbh": null,
		"jhzt": "1",
		"xzqh": "000000000",
		"zlcxsqr": null,
		"zldlssid": "0",
		"zldlxh": null,
		"zlsxczbs": null,
		"zlsfjs": "0",
		"zlsfzjsh": "1",
		"zlzgdw": null,
		"zlzgdwmc": null
	}, {
		"zlcode": "0000000002010102726583",
		"zlwfid": null,
		"activityid": null,
		"zljm": "28827",
		"zltitle": "国家税务总局　财政部　中国人民银行关于税务代保管资金账户管理有关问题的通知",
		"zlgjz": "代保管 资金 账户 管理",
		"zlflag": "1",
		"zltype": "“1“000000000102“,“1“000000000123“",
		"zlhytype": "00000000000000000000040",
		"zllywj": "0000000002010102726583.voc",
		"zlczwj": null,
		"zllrr": "总局超管",
		"zllrsj": "2012-10-17",
		"zllrdw": null,
		"zlzt": "60",
		"zlsfyx": "0",
		"zlsffb": "1",
		"zlfbr": "system",
		"zlly": null,
		"zlsz": "0",
		"zlwh": "国税发〔2007〕12号",
		"zlfwdw": "国家税务总局　财政部　中国人民银行",
		"zlbfrq": 1174355672000,
		"zlsxrq": null,
		"zlssrq": null,
		"zlwjdj": "3",
		"zlsydj": "0",
		"zlnowshr": null,
		"zlnowshjs": null,
		"zlnowjg": null,
		"zlnowbm": null,
		"zlzhczr": "zjsh",
		"zlzhczsj": 1350441551000,
		"lastczr": null,
		"zlqzz": null,
		"zlwxyy": null,
		"zlzy": null,
		"zlpz": "1-2-71",
		"zlsfgk": "0",
		"zlfbrq": 1350441551000,
		"zlcxyy": null,
		"zlnzoa": null,
		"zloaid": null,
		"zldq": "00000000",
		"zldqmc": "中华人民共和国",
		"zlfwzg": null,
		"zlsfdl": "0",
		"zlsfzcyh": "0",
		"zldxlx": "00000000000000000000003",
		"zldqbbh": "00000000000000000145778001",
		"zldffg": null,
		"zlxf": null,
		"zlywczr": null,
		"zltypemc": "税收法规->财务会计；税收法规->征收管理",
		"zlhytypemc": "通用政策",
		"zlfz": 29,
		"zlisdel": "0",
		"zlwzfgbh": null,
		"zldxlxmc": "全部",
		"zlcxlcid": null,
		"gxsj": null,
		"bbh": null,
		"jhzt": "1",
		"xzqh": "000000000",
		"zlcxsqr": null,
		"zldlssid": "0",
		"zldlxh": null,
		"zlsxczbs": null,
		"zlsfjs": "0",
		"zlsfzjsh": "1",
		"zlzgdw": null,
		"zlzgdwmc": null
	}, {
		"zlcode": "0000000002010102726581",
		"zlwfid": null,
		"activityid": null,
		"zljm": "28825",
		"zltitle": "国家税务总局关于按期开立税务代保管资金账户的通知",
		"zlgjz": "税务 代保管 资金 账户",
		"zlflag": "1",
		"zltype": "“1“000000000102“,“1“000000000123“",
		"zlhytype": "00000000000000000000040",
		"zllywj": "0000000002010102726581.voc",
		"zlczwj": null,
		"zllrr": "总局超管",
		"zllrsj": "2012-10-17",
		"zllrdw": null,
		"zlzt": "60",
		"zlsfyx": "0",
		"zlsffb": "1",
		"zlfbr": "system",
		"zlly": null,
		"zlsz": "0",
		"zlwh": "国税函〔2007〕717号",
		"zlfwdw": "国家税务总局",
		"zlbfrq": 1182736298000,
		"zlsxrq": null,
		"zlssrq": null,
		"zlwjdj": "3",
		"zlsydj": "0",
		"zlnowshr": null,
		"zlnowshjs": null,
		"zlnowjg": null,
		"zlnowbm": null,
		"zlzhczr": "zjsh",
		"zlzhczsj": 1350441378000,
		"lastczr": null,
		"zlqzz": null,
		"zlwxyy": null,
		"zlzy": null,
		"zlpz": "1-2-73",
		"zlsfgk": "0",
		"zlfbrq": 1350441378000,
		"zlcxyy": null,
		"zlnzoa": null,
		"zloaid": null,
		"zldq": "00000000",
		"zldqmc": "中华人民共和国",
		"zlfwzg": null,
		"zlsfdl": "0",
		"zlsfzcyh": "0",
		"zldxlx": "00000000000000000000003",
		"zldqbbh": "00000000000000000145776001",
		"zldffg": null,
		"zlxf": null,
		"zlywczr": null,
		"zltypemc": "税收法规->财务会计；税收法规->征收管理",
		"zlhytypemc": "通用政策",
		"zlfz": 0,
		"zlisdel": "0",
		"zlwzfgbh": null,
		"zldxlxmc": "全部",
		"zlcxlcid": null,
		"gxsj": null,
		"bbh": null,
		"jhzt": "1",
		"xzqh": "000000000",
		"zlcxsqr": null,
		"zldlssid": "0",
		"zldlxh": null,
		"zlsxczbs": null,
		"zlsfjs": "0",
		"zlsfzjsh": "1",
		"zlzgdw": null,
		"zlzgdwmc": null
	}, {
		"zlcode": "0000000002010102726576",
		"zlwfid": null,
		"activityid": null,
		"zljm": "28820",
		"zltitle": "国家税务总局　财政部关于严禁违规开立税款过渡账户的紧急通知",
		"zlgjz": "税款 账户",
		"zlflag": "1",
		"zltype": "“1“000000000102“,“1“000000000123“",
		"zlhytype": "00000000000000000000040",
		"zllywj": "0000000002010102726576.voc",
		"zlczwj": null,
		"zllrr": "总局超管",
		"zllrsj": "2012-10-17",
		"zllrdw": null,
		"zlzt": "60",
		"zlsfyx": "0",
		"zlsffb": "1",
		"zlfbr": "system",
		"zlly": null,
		"zlsz": "0",
		"zlwh": "国税发〔2008〕42号",
		"zlfwdw": "国家税务总局　财政部",
		"zlbfrq": 1209001852000,
		"zlsxrq": null,
		"zlssrq": null,
		"zlwjdj": "3",
		"zlsydj": "0",
		"zlnowshr": null,
		"zlnowshjs": null,
		"zlnowjg": null,
		"zlnowbm": null,
		"zlzhczr": "zjsh",
		"zlzhczsj": 1350441332000,
		"lastczr": null,
		"zlqzz": null,
		"zlwxyy": null,
		"zlzy": null,
		"zlpz": "1-2-82",
		"zlsfgk": "0",
		"zlfbrq": 1350441332000,
		"zlcxyy": null,
		"zlnzoa": null,
		"zloaid": null,
		"zldq": "00000000",
		"zldqmc": "中华人民共和国",
		"zlfwzg": null,
		"zlsfdl": "0",
		"zlsfzcyh": "0",
		"zldxlx": "00000000000000000000003",
		"zldqbbh": "00000000000000000145771001",
		"zldffg": null,
		"zlxf": null,
		"zlywczr": null,
		"zltypemc": "税收法规->财务会计；税收法规->征收管理",
		"zlhytypemc": "通用政策",
		"zlfz": 10,
		"zlisdel": "0",
		"zlwzfgbh": null,
		"zldxlxmc": "全部",
		"zlcxlcid": null,
		"gxsj": null,
		"bbh": null,
		"jhzt": "1",
		"xzqh": "000000000",
		"zlcxsqr": null,
		"zldlssid": "0",
		"zldlxh": null,
		"zlsxczbs": null,
		"zlsfjs": "0",
		"zlsfzjsh": "1",
		"zlzgdw": null,
		"zlzgdwmc": null
	}, {
		"zlcode": "0000000002010102726574",
		"zlwfid": null,
		"activityid": null,
		"zljm": "28818",
		"zltitle": "财政部关于跨省区水电项目税收分配的指导意见",
		"zlgjz": "跨省区 水电项目 税收 分配",
		"zlflag": "1",
		"zltype": "“1“000000000123“",
		"zlhytype": "00000000000000000000040",
		"zllywj": "0000000002010102726574.voc",
		"zlczwj": null,
		"zllrr": "总局超管",
		"zllrsj": "2012-10-17",
		"zllrdw": null,
		"zlzt": "60",
		"zlsfyx": "0",
		"zlsffb": "1",
		"zlfbr": "system",
		"zlly": null,
		"zlsz": "0",
		"zlwh": "财预〔2008〕84号",
		"zlfwdw": "财政部",
		"zlbfrq": 1213235419000,
		"zlsxrq": null,
		"zlssrq": null,
		"zlwjdj": "3",
		"zlsydj": "0",
		"zlnowshr": null,
		"zlnowshjs": null,
		"zlnowjg": null,
		"zlnowbm": null,
		"zlzhczr": "zjsh",
		"zlzhczsj": 1350441298000,
		"lastczr": null,
		"zlqzz": null,
		"zlwxyy": null,
		"zlzy": null,
		"zlpz": "1-2-84",
		"zlsfgk": "0",
		"zlfbrq": 1350441298000,
		"zlcxyy": null,
		"zlnzoa": null,
		"zloaid": null,
		"zldq": "00000000",
		"zldqmc": "中华人民共和国",
		"zlfwzg": null,
		"zlsfdl": "0",
		"zlsfzcyh": "0",
		"zldxlx": "00000000000000000000003",
		"zldqbbh": "00000000000000000145769001",
		"zldffg": null,
		"zlxf": null,
		"zlywczr": null,
		"zltypemc": "税收法规->财务会计",
		"zlhytypemc": "通用政策",
		"zlfz": 34,
		"zlisdel": "0",
		"zlwzfgbh": null,
		"zldxlxmc": "全部",
		"zlcxlcid": null,
		"gxsj": null,
		"bbh": null,
		"jhzt": "1",
		"xzqh": "000000000",
		"zlcxsqr": null,
		"zldlssid": "0",
		"zldlxh": null,
		"zlsxczbs": null,
		"zlsfjs": "0",
		"zlsfzjsh": "1",
		"zlzgdw": null,
		"zlzgdwmc": null
	}],
	"totalItems": 72,
	"totalPages": 3,
	"nextPage": 2,
	"prePage": 1,
	"sort": [{
		"property": "zllrsj",
		"dir": "desc"
	}],
	"orderBySetted": true,
	"offset": 0,
	"orderSortString": "zllrsj desc"
}